{
    "VPHB59H3": [],
    "BME350H1": [],
    "ITA492H5": [],
    "PMU261H1": [],
    "VIS203H1": [],
    "HST250H1": [],
    "FSL321Y1": [],
    "CCT361H5": [],
    "CCT404H5": [],
    "CHMB16H3": [],
    "VPMA93H3": [],
    "MATA33H3": [],
    "SMC380H1": [],
    "CSC367H5": [],
    "PMU390Y1": [],
    "MUZC22H3": [],
    "ANT350H5": [],
    "EESA01H3": [],
    "ENG330H5": [],
    "ENG483H1": [],
    "WGS372H5": [],
    "MGM320H5": [],
    "SOC445H5": [],
    "MGT453H5": [],
    "CIN240H1": [],
    "MUZB66H3": [],
    "EESB05H3": [],
    "WGS350H5": [],
    "GASD54H3": [],
    "CHI408H5": [],
    "EMU254H1": [],
    "MAT401H5": [],
    "MIE360H1": [],
    "HIS382H5": [],
    "EMU371H1": [],
    "JOUB03H3": [],
    "MAT223H5": [],
    "SOC205H1": [],
    "LIN353H5": [],
    "RSM219H1": [],
    "CCT353H5": [],
    "MAT294H1": [],
    "PMU187Y1": [],
    "DRE405H5": [],
    "PMA451Y1": [],
    "ECO325H5": [],
    "UTM190H5": [],
    "EMU263H1": [],
    "ECE316H1": [],
    "SOC412H5": [],
    "GASC57H3": [],
    "PHLC95H3": [],
    "CHM347H5": [],
    "CHI103H5": [],
    "MSE462H1": [],
    "ENG397H5": [],
    "FSL405H5": [],
    "PMA361Y1": [],
    "CSC384H1": [],
    "PHL310H5": [],
    "FREB11H3": [],
    "MAT315H1": [],
    "JMU101Y1": [],
    "ENV399Y1": [],
    "CCT419H5": [],
    "GASC41H3": [],
    "VCC308H5": [],
    "BIO412H5": [],
    "EMU262H1": [],
    "BIO260H1": [],
    "PHY146H5": [],
    "PHL322H1": [],
    "PSY374H5": [],
    "COPB14H3": [],
    "CCT222H5": [],
    "CCT260H5": [],
    "FSC439H5": [],
    "MGHC23H3": [],
    "HMB322H1": [],
    "IDSB10H3": [],
    "TMU132H1": [],
    "PHLD35H3": [],
    "ARC384H1": [],
    "EDS250H5": [],
    "CLA160H1": [],
    "JCP421H5": [],
    "MGED63H3": [],
    "CCT385H5": [],
    "ECE532H1": [],
    "BIO378H5": [],
    "MGT403Y1": [],
    "OMU701Y1": [],
    "HLTC02H3": [],
    "FAS143H5": [],
    "CITD06H3": [],
    "POL302Y5": [],
    "DRE201H5": [],
    "MUZC80H3": [],
    "SOC333H5": [],
    "PSYB90H3": [],
    "CIN491H1": [],
    "SOC352H5": [],
    "PHLD88Y3": [],
    "ENG305H5": [],
    "ARC382H1": [],
    "LGGB61H3": [],
    "ENGB71H3": [],
    "HIS104H5": [],
    "JMU185Y1": [],
    "MIE443H1": [],
    "PSY280H5": [],
    "SOCD40H3": [],
    "PMU326H1": [],
    "CHE332H1": [],
    "MUZB63H3": [],
    "ESC180H1": [],
    "ANTC41H3": [],
    "CRI480H1": [],
    "SOC363H5": [],
    "ECE342H1": [],
    "MGM101H5": [],
    "MIE263H1": [],
    "HSC301H5": [],
    "BIO406H5": [],
    "HIS299Y5": [],
    "HLTD12H3": [],
    "MDSC63H3": [],
    "SPA220Y5": [],
    "WRI375H5": [],
    "MIE250H1": [],
    "POLD92H3": [],
    "PHLD99H3": [],
    "MGEC38H3": [],
    "POLC88H3": [],
    "SOC440Y5": [],
    "PHL232H1": [],
    "SOCC49H3": [],
    "TEP327H1": [],
    "STAD78H3": [],
    "BIO360H5": [],
    "PSYC12H3": [],
    "HIN212H5": [],
    "ENGD95H3": [],
    "ASTB03H3": [],
    "VCC309H5": [],
    "GGR329H1": [],
    "OMU511H1": [],
    "GGR124H1": [],
    "CHM299Y1": [],
    "VPSC56H3": [],
    "ENG480H1": [],
    "HISB37H3": [],
    "MAT397H5": [],
    "EDS200H5": [],
    "CCT383H5": [],
    "PSY406H1": [],
    "HLTB31H3": [],
    "COPA84Y3": [],
    "PMU105Y1": [],
    "CHM361H5": [],
    "PHLB02H3": [],
    "ECO466H5": [],
    "MGT493H5": [],
    "ECE159H1": [],
    "MAT246H1": [],
    "STAD92H3": [],
    "CRTD44H3": [],
    "PSY493H1": [],
    "CSC301H5": [],
    "HLTC04H3": [],
    "RLG382H5": [],
    "ECE467H1": [],
    "CHE323H1": [],
    "UTM118H5": [],
    "CIV516H1": [],
    "CITC10H3": [],
    "IDSC08H3": [],
    "STAD93H3": [],
    "CRI210H1": [],
    "FSTA01H3": [],
    "MAT402H5": [],
    "MGM360H5": [],
    "ANTD05H3": [],
    "ENGC44H3": [],
    "PSCD50H3": [],
    "POL401Y5": [],
    "HISB30H3": [],
    "ESC195H1": [],
    "FAS258H5": [],
    "CHMC42H3": [],
    "FAS236H5": [],
    "PHL307H5": [],
    "JMU289Y1": [],
    "MGM222H5": [],
    "HIS393H1": [],
    "PSYC10H3": [],
    "EESB21H3": [],
    "ACT391H1": [],
    "MAT138H1": [],
    "GASD58H3": [],
    "BIOD12H3": [],
    "JAV152H1": [],
    "PMU484H1": [],
    "RSM270H1": [],
    "DTS301H5": [],
    "CIV576H1": [],
    "VPHC74H3": [],
    "ECO414H1": [],
    "MIE479H1": [],
    "THRC30H3": [],
    "STAB41H3": [],
    "NROC34H3": [],
    "CCT325H5": [],
    "CLA230H5": [],
    "PSY210H1": [],
    "PHY299Y5": [],
    "SOCB47H3": [],
    "CCT302H5": [],
    "PMU482Y1": [],
    "MAT497H5": [],
    "HLTA03H3": [],
    "EAS246H1": [],
    "SOC100H1": [],
    "MIE407H1": [],
    "STA388H5": [],
    "ENG274H5": [],
    "BME440H1": [],
    "ECE424H1": [],
    "CSC207H5": [],
    "FSC430H5": [],
    "ESC499H1": [],
    "COPA42Y3": [],
    "PHL345H5": [],
    "AST101H5": [],
    "FRED06H3": [],
    "PHL324H5": [],
    "MIE350H1": [],
    "PSY475H1": [],
    "APS163H1": [],
    "PSY399Y1": [],
    "ANTD19H3": [],
    "GGR246H1": [],
    "RLG362H5": [],
    "MDSC61H3": [],
    "CSCD90H3": [],
    "ENG385H1": [],
    "MGT341H5": [],
    "LIN456H5": [],
    "MIE429H1": [],
    "HLTD01H3": [],
    "SOCC27H3": [],
    "VIS202H1": [],
    "WGS215H5": [],
    "ENG396H5": [],
    "MGEC92H3": [],
    "VPSC77H3": [],
    "FAH295H5": [],
    "ANT402H5": [],
    "OMU621Y1": [],
    "MGAB02H3": [],
    "BME352H1": [],
    "SOC254H1": [],
    "CCT380H5": [],
    "ARA210H5": [],
    "SOC210H5": [],
    "ENGC14H3": [],
    "FAH270H1": [],
    "COPB53H3": [],
    "CIN360H1": [],
    "HMB302H1": [],
    "HISD64H3": [],
    "GASD53H3": [],
    "MAT188H1": [],
    "ACT240H1": [],
    "LAT201H1": [],
    "MSE332H1": [],
    "ECO349H5": [],
    "LINC13H3": [],
    "ARC467H1": [],
    "PMU285Y1": [],
    "CHM396H5": [],
    "POLC90H3": [],
    "LIN328H5": [],
    "MATA30H3": [],
    "HLTC24H3": [],
    "BCH311H1": [],
    "ENGA01H3": [],
    "CME262H1": [],
    "POL475H5": [],
    "ANTA02H3": [],
    "PMU189Y1": [],
    "SDS375H1": [],
    "HIS392H5": [],
    "MGFC30H3": [],
    "MAT337H1": [],
    "THRC15H3": [],
    "ENG349H5": [],
    "PHL220H5": [],
    "MGMD02H3": [],
    "FOR424H1": [],
    "CLA368H1": [],
    "ARC356H1": [],
    "GASB57H3": [],
    "APS113Y1": [],
    "CCT453H5": [],
    "ECE499Y1": [],
    "HMB299Y1": [],
    "BIOC12H3": [],
    "EMU151H1": [],
    "PMDB25H3": [],
    "SOC408H5": [],
    "TMU406H1": [],
    "NMC299Y1": [],
    "NROB61H3": [],
    "GGR376H5": [],
    "PHY293H1": [],
    "ECO314H1": [],
    "GGR379H5": [],
    "ENG316H5": [],
    "OMU509H1": [],
    "MIE258H1": [],
    "ANT430H5": [],
    "MGD426H5": [],
    "SOC366H5": [],
    "MSE403H1": [],
    "MSE461H1": [],
    "STA496H1": [],
    "VIS323H1": [],
    "ENG291H5": [],
    "WSTA03H3": [],
    "MIE345H1": [],
    "EESB19H3": [],
    "MGEC32H3": [],
    "HISD58H3": [],
    "JOUC62H3": [],
    "ENV399Y5": [],
    "MGT443H5": [],
    "CIV280H1": [],
    "CIN340H1": [],
    "GGRC31H3": [],
    "ARC385H1": [],
    "VIS303H1": [],
    "PSL399Y1": [],
    "CITC18H3": [],
    "PHYC54H3": [],
    "PHLD90H3": [],
    "FSL406H5": [],
    "PHL347H5": [],
    "ANT210H5": [],
    "ECE410H1": [],
    "PHYC11H3": [],
    "ACMD93Y3": [],
    "LIN410H5": [],
    "ENG424H5": [],
    "ECE335H1": [],
    "ANT404H5": [],
    "RSM319H1": [],
    "POL222H1": [],
    "GGRC41H3": [],
    "POLC11H3": [],
    "FSC371H5": [],
    "BIO403H5": [],
    "EMU430H1": [],
    "POL113H5": [],
    "JMU293Y1": [],
    "MIE542H1": [],
    "TMU409H1": [],
    "ENG234H5": [],
    "MDSC40H3": [],
    "THRC20H3": [],
    "MGT262H5": [],
    "AER373H1": [],
    "ECO375H1": [],
    "PMA487Y1": [],
    "NMC262H1": [],
    "CHM397H5": [],
    "ECE216H1": [],
    "MGT416H5": [],
    "ITA498H5": [],
    "MIE375H1": [],
    "HISB94H3": [],
    "ERS225H5": [],
    "GRK101H1": [],
    "MUZC60H3": [],
    "ECE353H1": [],
    "MIE320H1": [],
    "GASA01H3": [],
    "VPSD56H3": [],
    "SOC213H1": [],
    "CHE191H1": [],
    "VPSA62H3": [],
    "MAT240H5": [],
    "POL495Y1": [],
    "CCT409H5": [],
    "MGEB02H3": [],
    "MGT223H5": [],
    "JOUB18H3": [],
    "FREB01H3": [],
    "ARC251H1": [],
    "ECE461H1": [],
    "POLC65H3": [],
    "BME331H1": [],
    "PLID44H3": [],
    "ENG416H5": [],
    "SOC433H5": [],
    "MUZA62H3": [],
    "ITA399Y5": [],
    "ARC383H1": [],
    "STA218H5": [],
    "CCT410H5": [],
    "GGR325H5": [],
    "ANTB15H3": [],
    "PSYC73H3": [],
    "ECO325H1": [],
    "WSTC40H3": [],
    "OMU711H1": [],
    "ANTC10H3": [],
    "LIN325H5": [],
    "HPS210H1": [],
    "ECO303H5": [],
    "JEP356H5": [],
    "FOR308H1": [],
    "HSC307H5": [],
    "VIS404H1": [],
    "HIS484H5": [],
    "EMU130Y1": [],
    "CIN310H5": [],
    "SOC492H1": [],
    "JMU492Y1": [],
    "CIV549H1": [],
    "MGEA05H3": [],
    "PMU110Y1": [],
    "POLD98H3": [],
    "PMU415Y1": [],
    "RSM433H1": [],
    "SOCD20H3": [],
    "HIN411H5": [],
    "OMU710H1": [],
    "GGR314H1": [],
    "GGRD09H3": [],
    "GER100Y1": [],
    "EESC30H3": [],
    "THRA11H3": [],
    "EESC13H3": [],
    "BIOD33H3": [],
    "GGR370H5": [],
    "ENGC07H3": [],
    "LIN205H5": [],
    "SOC450H5": [],
    "ESTC34H3": [],
    "RSM221H1": [],
    "LINC28H3": [],
    "EESB04H3": [],
    "CIV523H1": [],
    "PSY299H5": [],
    "CIV214H1": [],
    "LINB06H3": [],
    "PHY332H5": [],
    "PHL245H1": [],
    "MATD01H3": [],
    "CHM394H5": [],
    "BIO324H5": [],
    "BIOC61H3": [],
    "DRS325H5": [],
    "ESS104H1": [],
    "MGAD40H3": [],
    "COPB52H3": [],
    "PPGD64H3": [],
    "POLC39H3": [],
    "LIN496H5": [],
    "ACTB40H3": [],
    "ENGB28H3": [],
    "POLC78H3": [],
    "ESS450H1": [],
    "CIN208H5": [],
    "ANT499H5": [],
    "ENGC41H3": [],
    "PLIC25H3": [],
    "MUZC02H3": [],
    "PHL375H1": [],
    "WRI483H5": [],
    "SOC219H5": [],
    "CCT457H5": [],
    "ENGD59H3": [],
    "MAT497Y1": [],
    "PMU115Y1": [],
    "STA413H5": [],
    "PHYA21H3": [],
    "PMU478Y1": [],
    "STAD70H3": [],
    "GGRC28H3": [],
    "FSC311H5": [],
    "HIS272H5": [],
    "CSCC63H3": [],
    "PSYD39H3": [],
    "PHLB09H3": [],
    "MUZA66H3": [],
    "MSE296H1": [],
    "CSCD58H3": [],
    "SOC394H1": [],
    "CHMB55H3": [],
    "VPSB85H3": [],
    "PSYC75H3": [],
    "CCT210H5": [],
    "MGT431H5": [],
    "PSYC59H3": [],
    "ITA437Y5": [],
    "ESC101H1": [],
    "HISB64H3": [],
    "CCT352H5": [],
    "AER372H1": [],
    "CHM220H1": [],
    "MGAD20H3": [],
    "ENG482H1": [],
    "PMU126H1": [],
    "CCT360H5": [],
    "MSE419H1": [],
    "LIN418H5": [],
    "PHL200Y1": [],
    "ECO206Y1": [],
    "STAC53H3": [],
    "MIE346H1": [],
    "MIE402H1": [],
    "CSCD37H3": [],
    "JMU391Y1": [],
    "MGHD24H3": [],
    "POL317H5": [],
    "IMI202H5": [],
    "ENGC37H3": [],
    "CITC02H3": [],
    "ECTD69H3": [],
    "ANT313H5": [],
    "MGAD65H3": [],
    "JOUA02H3": [],
    "LIN237H5": [],
    "MAT247H5": [],
    "ECO344H5": [],
    "MGY399Y1": [],
    "POLC09H3": [],
    "PLIC75H3": [],
    "RLG208H5": [],
    "HISC67H3": [],
    "PMU185Y1": [],
    "SOC402H5": [],
    "RLG313H5": [],
    "JOUA01H3": [],
    "PSL299Y1": [],
    "CRTC72H3": [],
    "ECTB61H3": [],
    "JOUB39H3": [],
    "PMDB33H3": [],
    "CSCD25H3": [],
    "PHL374H5": [],
    "PSY405H1": [],
    "ECO428H1": [],
    "RLG323H5": [],
    "ENGB35H3": [],
    "ENG213H5": [],
    "PSYD16H3": [],
    "FAH246H1": [],
    "ENG275H5": [],
    "PMU363Y1": [],
    "ANT310H5": [],
    "FSC350H5": [],
    "MMU100H1": [],
    "CDPD00H3": [],
    "JGJ360H1": [],
    "MIE408H1": [],
    "POLD30H3": [],
    "IDSC20H3": [],
    "SOC205H5": [],
    "HMU450H1": [],
    "ESTB02H3": [],
    "PHLB35H3": [],
    "PMDB41H3": [],
    "CIV324H1": [],
    "ENGB38H3": [],
    "ENG358H5": [],
    "CSC290H5": [],
    "MIE366H1": [],
    "PHY333H5": [],
    "BIO434H5": [],
    "PSY315H5": [],
    "SLA100H1": [],
    "RLG399Y5": [],
    "HIS377H1": [],
    "ENGD53H3": [],
    "PSL379H1": [],
    "PSY402H5": [],
    "ANT331H5": [],
    "PHL235H5": [],
    "ECE421H1": [],
    "CJH332H1": [],
    "JMU285Y1": [],
    "ARC367H1": [],
    "GASB30H3": [],
    "MIE100H1": [],
    "CSC493H5": [],
    "PHYC50H3": [],
    "POL399Y5": [],
    "MGT231H5": [],
    "CSC148H5": [],
    "IDSC14H3": [],
    "TMU314Y1": [],
    "STA399Y5": [],
    "BIOD07H3": [],
    "ECO359H1": [],
    "HIS102Y1": [],
    "ROB310H1": [],
    "PMU410Y1": [],
    "CSC148H1": [],
    "PHL495H1": [],
    "APS511H1": [],
    "UNI495Y1": [],
    "ITA342H5": [],
    "PMA492Y1": [],
    "HMB202H1": [],
    "LGGA82Y3": [],
    "WRI173H5": [],
    "MGMD10H3": [],
    "MGID40H3": [],
    "HIS393H5": [],
    "PSY480H5": [],
    "PMU283Y1": [],
    "PMU405Y1": [],
    "BIOC54H3": [],
    "MGSC05H3": [],
    "CIV477H1": [],
    "PSY270H5": [],
    "EESC34H3": [],
    "OMU606Y1": [],
    "FREC38H3": [],
    "PHLC80H3": [],
    "EMU267H1": [],
    "MGM365H5": [],
    "ANT241H5": [],
    "MSE435H1": [],
    "ARC280H1": [],
    "WSTC12H3": [],
    "POL232H1": [],
    "SOC263H5": [],
    "FAS446Y5": [],
    "LIN360H5": [],
    "GGR377H5": [],
    "PHY399Y1": [],
    "MGMD01H3": [],
    "NMEB10H3": [],
    "HLTC52H3": [],
    "FRE440H5": [],
    "BIO153H5": [],
    "CSC324H5": [],
    "PHY325H5": [],
    "ANTC47H3": [],
    "PSY210H5": [],
    "EMU401H1": [],
    "HLTD08H3": [],
    "ECO380H5": [],
    "EESD07H3": [],
    "JMU210H1": [],
    "ANTC04H3": [],
    "CIN492H1": [],
    "MSE335H1": [],
    "BIOC14H3": [],
    "PHY254H1": [],
    "WRI411H5": [],
    "ANT202H5": [],
    "PSYC36H3": [],
    "ISP010H5": [],
    "AER315H1": [],
    "ENG252H1": [],
    "TEP445H1": [],
    "EMU435H1": [],
    "TEP444H1": [],
    "ANT433H5": [],
    "PMU163Y1": [],
    "ANT207H1": [],
    "CHI312H5": [],
    "PHL340H1": [],
    "EAS396H1": [],
    "PMU230Y1": [],
    "FAH215H5": [],
    "ENGD48H3": [],
    "ECO400Y5": [],
    "NMEB08H3": [],
    "SOCD51H3": [],
    "PSY240H1": [],
    "ENV493H1": [],
    "CLA301H5": [],
    "MSE160H1": [],
    "SOC228H5": [],
    "CSCB36H3": [],
    "PMU264Y1": [],
    "FRE355H5": [],
    "PHY256H1": [],
    "CLA233H5": [],
    "PMDC42Y3": [],
    "ENG370H5": [],
    "PMU251Y1": [],
    "CCT225H5": [],
    "FAH101H5": [],
    "PSL378H1": [],
    "ANTB66H3": [],
    "ECE286H1": [],
    "CCT483H5": [],
    "ENG235H5": [],
    "HIS493H5": [],
    "MGT252H5": [],
    "LIN229H5": [],
    "GGR337H5": [],
    "TEP326H1": [],
    "PSYC02H3": [],
    "MUZA63H3": [],
    "ENG344H5": [],
    "PHL275H5": [],
    "ENG341H5": [],
    "EESD17Y3": [],
    "MGT452H5": [],
    "FREA97H3": [],
    "ENG279H5": [],
    "HISD36H3": [],
    "ENGB30H3": [],
    "MIE253H1": [],
    "CSCD27H3": [],
    "HLTB40H3": [],
    "FSC489H5": [],
    "ANT209H5": [],
    "MGT394H5": [],
    "MGEC45H3": [],
    "VPAC13H3": [],
    "ENG371H5": [],
    "PHLB06H3": [],
    "POLC57H3": [],
    "ENGC04H3": [],
    "ANTD35H3": [],
    "BIO354H5": [],
    "ENG211H5": [],
    "FRE325H5": [],
    "CSC399Y5": [],
    "BIO342H5": [],
    "STAB23H3": [],
    "SOC353H5": [],
    "SPA259H1": [],
    "EAS120Y1": [],
    "MGT232H5": [],
    "TMU430H1": [],
    "VPHA46H3": [],
    "CIV416H1": [],
    "HIS214H5": [],
    "VPHB63H3": [],
    "WGS420H5": [],
    "CSC311H5": [],
    "CCT212H5": [],
    "JMU499H1": [],
    "APS500H1": [],
    "MGT225H5": [],
    "PSYC24H3": [],
    "HLTC23H3": [],
    "GGR374H5": [],
    "FREC02H3": [],
    "ENGC01H3": [],
    "ERS402H5": [],
    "CCT211H5": [],
    "CCT382H5": [],
    "MGOC20H3": [],
    "PHL376H5": [],
    "CHI411H5": [],
    "CLA204H1": [],
    "SOC448H5": [],
    "FAH274H5": [],
    "EESC33H3": [],
    "BIOD23H3": [],
    "MIE334H1": [],
    "GGRC24H3": [],
    "ANT333H5": [],
    "ENV332H5": [],
    "JAV120H1": [],
    "UTM197H5": [],
    "CHM412H5": [],
    "MAT499Y1": [],
    "RLG349H5": [],
    "MATA22H3": [],
    "MAT237Y1": [],
    "ECE466H1": [],
    "CHE564H1": [],
    "ERS325H5": [],
    "RSM490H1": [],
    "ARC456H1": [],
    "ERS472H5": [],
    "SOCC51H3": [],
    "PSYD10H3": [],
    "SAH200H5": [],
    "ANT346H1": [],
    "PHL113H5": [],
    "MIE363H1": [],
    "WGS411Y5": [],
    "CCT399Y5": [],
    "SOC222H5": [],
    "CME525H1": [],
    "MIN400H1": [],
    "ENG215H5": [],
    "ANT358H5": [],
    "CIV201H1": [],
    "SOC421H5": [],
    "EMU150H1": [],
    "SOC439Y5": [],
    "PSY397H1": [],
    "SOC425H5": [],
    "ITA421H5": [],
    "ENG375H5": [],
    "MGEC82H3": [],
    "VPSB86H3": [],
    "VPSB58H3": [],
    "CITD30H3": [],
    "FRED03H3": [],
    "BIO361H5": [],
    "PEY200H5": [],
    "MUZB80H3": [],
    "MIE439H1": [],
    "MGT492H5": [],
    "HISB58H3": [],
    "MGSC20H3": [],
    "PMU300H1": [],
    "SOC282H1": [],
    "HIS401H5": [],
    "HISA08H3": [],
    "BIOD21H3": [],
    "ENGC21H3": [],
    "MGT150H5": [],
    "MGED11H3": [],
    "VCC492H5": [],
    "ENG352H5": [],
    "GGRD49H3": [],
    "GGR387H5": [],
    "RLG490Y1": [],
    "MGT420H5": [],
    "GGR307H5": [],
    "CCT357H5": [],
    "BIOD29H3": [],
    "FAH207H1": [],
    "STA457H1": [],
    "ENG140Y1": [],
    "LINB18H3": [],
    "CITD12H3": [],
    "ECO202Y1": [],
    "ECE360H1": [],
    "HIS308H5": [],
    "LIN411H5": [],
    "SOC360H1": [],
    "JMU491Y1": [],
    "LIN204H5": [],
    "HISB63H3": [],
    "JOUB02H3": [],
    "ENG341H1": [],
    "FAH496H5": [],
    "PHLC43H3": [],
    "CLAB20H3": [],
    "PSY471H5": [],
    "FAH433H1": [],
    "ANT351H5": [],
    "ECE368H1": [],
    "EESC19H3": [],
    "PSYC93H3": [],
    "SOC496H1": [],
    "LGGC62H3": [],
    "IDSC01H3": [],
    "ECE354H1": [],
    "WGS210H5": [],
    "MGT421H5": [],
    "SOC351H5": [],
    "PMU340Y1": [],
    "PMDB36H3": [],
    "CHM299Y5": [],
    "GGR382H5": [],
    "NEW324H1": [],
    "ENG460H5": [],
    "MDSB62H3": [],
    "CHE374H1": [],
    "PHYD01H3": [],
    "EMU499H1": [],
    "ENG340H1": [],
    "VCC290H5": [],
    "HISD09H3": [],
    "ISP130H5": [],
    "ENG215H1": [],
    "PHY137H5": [],
    "PSY220H1": [],
    "GGRD12H3": [],
    "HISD53H3": [],
    "JCP321H5": [],
    "SOCB05H3": [],
    "LIN495Y1": [],
    "VPAD14H3": [],
    "HLTD26H3": [],
    "ANT215H5": [],
    "WRI340H5": [],
    "BIOD65H3": [],
    "PMA478Y1": [],
    "POLB50Y3": [],
    "BIO362H5": [],
    "PHLB07H3": [],
    "PMU271Y1": [],
    "PMU454Y1": [],
    "ECE313H1": [],
    "ESC102H1": [],
    "CIV578H1": [],
    "ENGD52H3": [],
    "CSC207H1": [],
    "ENG335H5": [],
    "CIN403H5": [],
    "VPSB70H3": [],
    "MAT137Y1": [],
    "ARC355H1": [],
    "CIV382Y1": [],
    "RSM299Y1": [],
    "PHLC86H3": [],
    "APS420H1": [],
    "SOCB37H3": [],
    "HIS462H5": [],
    "JMU421H1": [],
    "PHY343H5": [],
    "HISB40H3": [],
    "WRI365Y5": [],
    "GER100Y5": [],
    "LIN102H1": [],
    "WGS337H5": [],
    "ANT208H5": [],
    "HMB472H1": [],
    "POL363H1": [],
    "ENG489Y5": [],
    "FSC402H5": [],
    "MGEC02H3": [],
    "LIN486H5": [],
    "ECE417H1": [],
    "VPHB74H3": [],
    "FAH481H1": [],
    "MDSB63H3": [],
    "SOCB26H3": [],
    "PSCD11H3": [],
    "SOCA03Y3": [],
    "PHL283H5": [],
    "MGAC50H3": [],
    "POL310Y5": [],
    "LTE299Y1": [],
    "ENGB32H3": [],
    "PSY345H5": [],
    "POL349H1": [],
    "WRI410H5": [],
    "PHLB31H3": [],
    "MDSA02H3": [],
    "HIS284H5": [],
    "SMU400H1": [],
    "PHL475H5": [],
    "SOCC30H3": [],
    "PMU391Y1": [],
    "ENG269H5": [],
    "CIV380H1": [],
    "ENV200H1": [],
    "ECE345H1": [],
    "LIN498H1": [],
    "HMU323H1": [],
    "VPSB73H3": [],
    "JMU104Y1": [],
    "STAD94H3": [],
    "MIE520H1": [],
    "ANTC17H3": [],
    "SPA220Y1": [],
    "SLA212H1": [],
    "ENG366H5": [],
    "MGTA36H3": [],
    "MAT302H5": [],
    "MATA31H3": [],
    "EESD06H3": [],
    "JOUB19H3": [],
    "WGS202H5": [],
    "EDS275H5": [],
    "MIE367H1": [],
    "GGRB05H3": [],
    "FRE391H5": [],
    "HISD54H3": [],
    "PSY343H1": [],
    "FREC12H3": [],
    "VIS313H1": [],
    "JAV200H1": [],
    "EESD21H3": [],
    "MGAD70H3": [],
    "FSC401H5": [],
    "CHM247H1": [],
    "TMU231H1": [],
    "MIE507H1": [],
    "GGRC26H3": [],
    "ENGC45H3": [],
    "WSTB20H3": [],
    "WRI490H5": [],
    "POL210H5": [],
    "CHM136H1": [],
    "SOC252H1": [],
    "CCT486H5": [],
    "ANTD13H3": [],
    "NEW391H1": [],
    "CME368H1": [],
    "FREB02H3": [],
    "ECE537H1": [],
    "MDSB10H3": [],
    "PMA491Y1": [],
    "EEB397Y1": [],
    "HLTC22H3": [],
    "ECO456H5": [],
    "CHM397H0": [],
    "DRS121H5": [],
    "PCL397Y0": [],
    "MATD92H3": [],
    "ENG301H5": [],
    "MAT296H1": [],
    "RLG371H5": [],
    "HISD03H3": [],
    "RLG101H5": [],
    "PSY400Y5": [],
    "JAL253H5": [],
    "STA314H5": [],
    "FRE353H5": [],
    "ENG394H5": [],
    "GGR201H5": [],
    "CHM101H5": [],
    "BIOD26H3": [],
    "MATA36H3": [],
    "SOCC26H3": [],
    "SOC362H5": [],
    "CHMD91H3": [],
    "SOC494H1": [],
    "POL390H5": [],
    "MGT411H5": [],
    "GGR349H5": [],
    "CSCC85H3": [],
    "HSC405H5": [],
    "HPS496H1": [],
    "PSY343H5": [],
    "CHM485H5": [],
    "PHLD96H3": [],
    "SOC201H1": [],
    "FRE316H5": [],
    "DRE121H5": [],
    "ANT418H5": [],
    "MGT434H5": [],
    "WRI273H5": [],
    "ARC457Y1": [],
    "MGT201H5": [],
    "HLTA02H3": [],
    "EAS284H1": [],
    "VPHB68H3": [],
    "MATD67H3": [],
    "MUZA61H3": [],
    "HIS420H5": [],
    "CLA308H5": [],
    "HMB443H1": [],
    "HISC18H3": [],
    "FRE393H5": [],
    "CSC299Y1": [],
    "GGR217H5": [],
    "PMA454Y1": [],
    "CSC209H1": [],
    "MAT136H1": [],
    "VIS201H1": [],
    "POL320Y1": [],
    "MAT187H1": [],
    "PMU282Y1": [],
    "SMC481Y1": [],
    "ITA495H1": [],
    "IDSB06H3": [],
    "SOCB42H3": [],
    "LIN204H1": [],
    "SOCD15H3": [],
    "FAH493H5": [],
    "MIE376H1": [],
    "SOC330H5": [],
    "MSE245H1": [],
    "MGFD30H3": [],
    "MUZC01H3": [],
    "ENG223H5": [],
    "TMU230H1": [],
    "CHE469H1": [],
    "CLA204H5": [],
    "SOC361H5": [],
    "FSTB01H3": [],
    "GGRD25H3": [],
    "SOC452H5": [],
    "VPSB90H3": [],
    "JMU193Y1": [],
    "GGR322H5": [],
    "JMU317Y1": [],
    "DRE380H5": [],
    "POL410H1": [],
    "PSYC19H3": [],
    "IRE431H1": [],
    "SOCD41H3": [],
    "PHL265H5": [],
    "MGAC01H3": [],
    "MIE312H1": [],
    "ENG315H5": [],
    "ARC252H1": [],
    "GER200Y5": [],
    "UTM101H5": [],
    "SPA100Y1": [],
    "ECE472H1": [],
    "HLTD50H3": [],
    "HIS389H1": [],
    "EDS388H5": [],
    "CSC420H5": [],
    "HIS271H5": [],
    "HIS340H5": [],
    "LIN327H5": [],
    "LIN288H5": [],
    "ECO433H5": [],
    "STA237H1": [],
    "GGR320H1": [],
    "PMU290Y1": [],
    "MGT330H5": [],
    "MIE566H1": [],
    "PHYB21H3": [],
    "MAT327H1": [],
    "PMU389Y1": [],
    "MIN466H1": [],
    "POL360H1": [],
    "ITA100Y1": [],
    "LGGA60H3": [],
    "WSTD01H3": [],
    "HIS397H5": [],
    "CHMD16H3": [],
    "CLA232H1": [],
    "MGMA01H3": [],
    "WRI430H5": [],
    "CCT331H5": [],
    "ENG386H5": [],
    "MDSC80H3": [],
    "HMU305H1": [],
    "CHM489Y5": [],
    "BIOD13H3": [],
    "MGEA06H3": [],
    "GGR201H1": [],
    "SOC432H5": [],
    "ANT352H5": [],
    "UTM115H5": [],
    "BIO410H5": [],
    "BIO211H5": [],
    "DRS322H5": [],
    "BIO325H5": [],
    "VPSB74H3": [],
    "APM346H1": [],
    "RLG350H5": [],
    "ENG102H1": [],
    "BIOB52H3": [],
    "RLG422H5": [],
    "ACT230H1": [],
    "SOC221H5": [],
    "MAT295H1": [],
    "HLTB15H3": [],
    "SOC403H5": [],
    "CCT334H5": [],
    "ECO302H5": [],
    "ENG323H5": [],
    "JMU191Y1": [],
    "BIOB11H3": [],
    "MAT157Y5": [],
    "ANT439H5": [],
    "JPI201H1": [],
    "CHMC16H3": [],
    "FSC271H5": [],
    "BIOC99H3": [],
    "COPC99H3": [],
    "GGRB13H3": [],
    "CLA365H5": [],
    "HIS204H5": [],
    "CSC476H5": [],
    "CHE462H1": [],
    "SOC356H5": [],
    "PHL200H5": [],
    "CSCC24H3": [],
    "PHYB10H3": [],
    "TRN299Y1": [],
    "GGR362H5": [],
    "MIE414H1": [],
    "SOC329H5": [],
    "OMU603Y1": [],
    "SOC350H1": [],
    "HLTC47H3": [],
    "EEB497H1": [],
    "ENGD03H3": [],
    "DRS221H5": [],
    "IDSD10H3": [],
    "ESS392Y1": [],
    "ECO320Y5": [],
    "PHL271H5": [],
    "CPS489Y5": [],
    "PHL239H5": [],
    "GGR494H5": [],
    "ECTC61H3": [],
    "NMC263H1": [],
    "POL111H5": [],
    "MAT496H1": [],
    "HISC66H3": [],
    "SOC341H5": [],
    "CCT412H5": [],
    "HISB12H3": [],
    "WGS354H5": [],
    "SOC351H1": [],
    "SPA320Y1": [],
    "HIS343H1": [],
    "BIOD95H3": [],
    "CCT461H5": [],
    "OMU721Y1": [],
    "HISB03H3": [],
    "HMU225H1": [],
    "SOC350H5": [],
    "ENV495H5": [],
    "PSY372H1": [],
    "CHE112H1": [],
    "ECE462H1": [],
    "IDSD12H3": [],
    "ECO365H5": [],
    "THRC50H3": [],
    "MIN565H1": [],
    "ANT334H5": [],
    "APS112H1": [],
    "WRI380H5": [],
    "FAS145H5": [],
    "PSY299Y5": [],
    "ANT431H5": [],
    "PHLD98H3": [],
    "HMU359H1": [],
    "LIN399Y5": [],
    "BIO326H5": [],
    "PSY351H5": [],
    "MSE297H1": [],
    "HMU426H1": [],
    "PMU098H1": [],
    "MIE313H1": [],
    "WRI310H5": [],
    "POL485H5": [],
    "PMU339Y1": [],
    "ANT205H5": [],
    "MATC46H3": [],
    "PHC435H1": [],
    "RLGA01H3": [],
    "JMU493Y1": [],
    "HST451Y1": [],
    "CSCB07H3": [],
    "MUZA80H3": [],
    "PHLB05H3": [],
    "SPA235H5": [],
    "ANT340H5": [],
    "ITA350H5": [],
    "SOCC11H3": [],
    "PSY230H5": [],
    "CIV550H1": [],
    "MIE221H1": [],
    "ENGD26Y3": [],
    "COPA82Y3": [],
    "WRI225H5": [],
    "ANT361H5": [],
    "FSC370H5": [],
    "EESD13H3": [],
    "MIE561H1": [],
    "FRE343H5": [],
    "NMC252H1": [],
    "CIN290H5": [],
    "CSCD84H3": [],
    "CSC373H5": [],
    "ECE244H1": [],
    "PSY309H5": [],
    "ECE363H1": [],
    "VPSB80H3": [],
    "ANTB05H3": [],
    "EEB386H1": [],
    "VIS220H1": [],
    "BIOC63H3": [],
    "PHL350H5": [],
    "SOCC31H3": [],
    "NROD98Y3": [],
    "WGS451H1": [],
    "CSCC73H3": [],
    "ECO316H1": [],
    "ECO420Y5": [],
    "CLA237H5": [],
    "ANTD31H3": [],
    "BME330H1": [],
    "PSY327H5": [],
    "HIS498Y5": [],
    "PRT100Y1": [],
    "FRE388H5": [],
    "PHY479Y1": [],
    "CCT324H5": [],
    "JOUC20H3": [],
    "PSY201H1": [],
    "MGMD21H3": [],
    "CITA01H3": [],
    "ANT348H1": [],
    "CSC420H1": [],
    "OMU609H1": [],
    "MGM364H5": [],
    "ANT363H5": [],
    "PHL433H5": [],
    "VPSB76H3": [],
    "UTM111H5": [],
    "GGRB28H3": [],
    "VIC296H1": [],
    "MGEC31H3": [],
    "PHLA11H3": [],
    "MIE562H1": [],
    "POLD09H3": [],
    "PSY399Y5": [],
    "PHL365H5": [],
    "RLG232H1": [],
    "ARC486H1": [],
    "ARA412Y5": [],
    "CIV342H1": [],
    "BIOD99Y3": [],
    "IMI201H5": [],
    "GGRA30H3": [],
    "MGEC34H3": [],
    "HISD16H3": [],
    "HIS368H1": [],
    "ENGB63H3": [],
    "HIS200H5": [],
    "PHLD91H3": [],
    "PMU392Y1": [],
    "MAT236H5": [],
    "ECE356H1": [],
    "VIS212H1": [],
    "COPA91Y3": [],
    "LIN233H5": [],
    "PSYB70H3": [],
    "MIE222H1": [],
    "FAS243H5": [],
    "LIN299Y1": [],
    "EMU270H1": [],
    "PSY320H5": [],
    "PHL210Y5": [],
    "MAT231H1": [],
    "MUZC62H3": [],
    "WGS101H5": [],
    "PMU184Y1": [],
    "MGTA01H3": [],
    "MGHC52H3": [],
    "CHE304H1": [],
    "HISA09H3": [],
    "PSYD51H3": [],
    "POL405Y5": [],
    "MGY250H1": [],
    "PHL497H5": [],
    "MGEC37H3": [],
    "POL354H5": [],
    "PSYA02H3": [],
    "CHE353H1": [],
    "ENG426H5": [],
    "PHL217H1": [],
    "CLA231H1": [],
    "PSYC70H3": [],
    "IDSB11H3": [],
    "CIN400H5": [],
    "ENGC90H3": [],
    "MGFD15H3": [],
    "CHM462H5": [],
    "ECE419H1": [],
    "POL378H1": [],
    "MUZC63H3": [],
    "MIE404H1": [],
    "NMC471H1": [],
    "MGTA35H3": [],
    "RLG317H1": [],
    "MATD95H3": [],
    "HLTD23H3": [],
    "ENGB74H3": [],
    "POL320Y5": [],
    "TEP281H1": [],
    "VPAB13H3": [],
    "PHL341H5": [],
    "HISD70H3": [],
    "IRE242H1": [],
    "ANTD41H3": [],
    "SOC386H1": [],
    "POL318H5": [],
    "JOUB14H3": [],
    "ENG481H1": [],
    "HPS301H1": [],
    "AFSC55H3": [],
    "TEP448H1": [],
    "PHL388H1": [],
    "VIS321H1": [],
    "ARC352H1": [],
    "ENG237H1": [],
    "ARC100H1": [],
    "PMU483Y1": [],
    "VPHC54H3": [],
    "WGS271Y1": [],
    "PLID34H3": [],
    "STA378H5": [],
    "FAH385H5": [],
    "POLB91H3": [],
    "FAH281H5": [],
    "BIOC60H3": [],
    "JMU389Y1": [],
    "MIE365H1": [],
    "POLC73H3": [],
    "PSYC14H3": [],
    "SOC323H5": [],
    "HPS100H1": [],
    "MSE415H1": [],
    "MAT292H1": [],
    "PSY260H1": [],
    "GGRC12H3": [],
    "CIV541H1": [],
    "ECE302H1": [],
    "PSY353H5": [],
    "VIS205H1": [],
    "LIN487H5": [],
    "CHMA12H3": [],
    "ENG327H5": [],
    "IDSD15H3": [],
    "RLG209H5": [],
    "POLD90H3": [],
    "CHM242H5": [],
    "RLG311H5": [],
    "GGRA03H3": [],
    "EMU417H1": [],
    "GGR497H5": [],
    "EAS257H1": [],
    "PHLC07H3": [],
    "VPSD63H3": [],
    "FAH335H1": [],
    "WGS351H5": [],
    "MIN329H1": [],
    "MGT428H5": [],
    "MGT442H5": [],
    "HIS330H1": [],
    "EMU355Y1": [],
    "PMU182Y1": [],
    "CIV340H1": [],
    "PHY473H5": [],
    "MIE563H1": [],
    "ENGC86H3": [],
    "ANT466H5": [],
    "ENGC28H3": [],
    "HIS499H5": [],
    "FCS292H1": [],
    "MIE335H1": [],
    "RLG464H5": [],
    "EEB299Y1": [],
    "MGEC81H3": [],
    "ENG304H5": [],
    "ENG121H5": [],
    "HIS218H1": [],
    "EESC07H3": [],
    "BIOC32H3": [],
    "FRE272H1": [],
    "CLAA05H3": [],
    "ENG323H1": [],
    "ITA451H5": [],
    "RLG499Y5": [],
    "PSYD31H3": [],
    "RSM220H1": [],
    "JCP322H5": [],
    "HLTC26H3": [],
    "OMU703Y1": [],
    "ENGC13H3": [],
    "SMU200H1": [],
    "PLID50H3": [],
    "EESB03H3": [],
    "MATC09H3": [],
    "VIS332H1": [],
    "PLIC24H3": [],
    "CHE222H1": [],
    "BIOD25H3": [],
    "MGMB01H3": [],
    "MGT480H5": [],
    "CSB201H1": [],
    "CHMD90Y3": [],
    "THRC55H3": [],
    "GGR207H5": [],
    "PMU191Y1": [],
    "LIN229H1": [],
    "OMU705H1": [],
    "CSC427H5": [],
    "IMM350H1": [],
    "EEB214H1": [],
    "CLA395H5": [],
    "FRE376H5": [],
    "CHM135H1": [],
    "ECE463H1": [],
    "ANTC27H3": [],
    "PHY100H5": [],
    "FAS345Y5": [],
    "SMC457H1": [],
    "GGRC02H3": [],
    "OMU504Y1": [],
    "ECO312H5": [],
    "HIS339H5": [],
    "PHL240H1": [],
    "POLD42H3": [],
    "HLTC51H3": [],
    "PSY308H1": [],
    "CSC393H5": [],
    "HIS391H5": [],
    "ENGD02Y3": [],
    "POL496H5": [],
    "LINB29H3": [],
    "POLC32H3": [],
    "GGRC40H3": [],
    "ECO349H1": [],
    "HIS499Y1": [],
    "BIO404H5": [],
    "FAH332H5": [],
    "CCT351H5": [],
    "MAT185H1": [],
    "CRI322H1": [],
    "COPB50H3": [],
    "PHLC06H3": [],
    "ENG102H5": [],
    "CCT305H5": [],
    "HSC302H5": [],
    "PHL313H1": [],
    "HIS385H1": [],
    "MIN120H1": [],
    "SOC485H5": [],
    "JMU484Y1": [],
    "CSCD92H3": [],
    "STA258H5": [],
    "MATD44H3": [],
    "MAT495H1": [],
    "MGAC02H3": [],
    "ECO333H1": [],
    "GGRA02H3": [],
    "IMM340H1": [],
    "HIS292H1": [],
    "BIO201H5": [],
    "BME410H1": [],
    "GGRB02H3": [],
    "FREC18H3": [],
    "SOC460H5": [],
    "CCT449H5": [],
    "ITA201Y5": [],
    "ENG392H5": [],
    "LGGA90Y3": [],
    "RSM424H1": [],
    "ECO204Y5": [],
    "CSC108H5": [],
    "FAH488H5": [],
    "PMU330Y1": [],
    "RSM430H1": [],
    "SMC480H1": [],
    "CHE324H1": [],
    "POLA02H3": [],
    "PSY321H5": [],
    "HISB31H3": [],
    "CIV332H1": [],
    "PHL302H5": [],
    "PMU490Y1": [],
    "HIS290H5": [],
    "MGT324H5": [],
    "MUZA67H3": [],
    "ENGD50H3": [],
    "DTS202H5": [],
    "JMU201Y1": [],
    "MIN301H1": [],
    "PHL273H1": [],
    "MGEC93H3": [],
    "JMU485Y1": [],
    "TMU140Y1": [],
    "MGSD15H3": [],
    "CHM243H5": [],
    "ENGC24H3": [],
    "PSYD11H3": [],
    "VIS209H1": [],
    "BIO314H5": [],
    "EESD02H3": [],
    "STA347H1": [],
    "HPS302H1": [],
    "HIS250H5": [],
    "MDSC66H3": [],
    "HIS400H1": [],
    "RSM260H1": [],
    "ECE430H1": [],
    "POL343Y5": [],
    "PHL409H1": [],
    "POL305H5": [],
    "SOC316H5": [],
    "CLA319H5": [],
    "CCT110H5": [],
    "CIV312H1": [],
    "STAD57H3": [],
    "SOC338H5": [],
    "ANTB80H3": [],
    "ECE496Y1": [],
    "CSCC43H3": [],
    "JMU291Y1": [],
    "HSC401H5": [],
    "FRE383H5": [],
    "ENGB31H3": [],
    "MIE231H1": [],
    "PMU299Y1": [],
    "EMU372Y1": [],
    "ENG463H5": [],
    "MDSC02H3": [],
    "ECO351H5": [],
    "CCT304H5": [],
    "PMDC56H3": [],
    "ECO220Y1": [],
    "WSTC25H3": [],
    "POLC16H3": [],
    "MGEB11H3": [],
    "PHL447H5": [],
    "SOC244H5": [],
    "LIND03H3": [],
    "BIOC39H3": [],
    "GGR407H5": [],
    "PHYA10H3": [],
    "CLA390H5": [],
    "ENG311H5": [],
    "ANT211H5": [],
    "MAT136H5": [],
    "STAA57H3": [],
    "OMU601Y1": [],
    "OMU709H1": [],
    "ESC204H1": [],
    "HIS310H5": [],
    "LAT221H5": [],
    "DRS321H5": [],
    "CSCD43H3": [],
    "HIS285H5": [],
    "PMU388Y1": [],
    "POL487H5": [],
    "CCT303H5": [],
    "RLG205H5": [],
    "EMU252H1": [],
    "ECE297H1": [],
    "MIN470H1": [],
    "STA220H1": [],
    "MIE236H1": [],
    "ENGD62H3": [],
    "ITA371H5": [],
    "VIS320H1": [],
    "STA215H5": [],
    "PEY500Y1": [],
    "ENGA02H3": [],
    "ESTD19H3": [],
    "ANT436H5": [],
    "SOC390Y1": [],
    "POL379H1": [],
    "POL443Y5": [],
    "FRE382H5": [],
    "FREC46H3": [],
    "PSYC18H3": [],
    "AER406H1": [],
    "CME270H1": [],
    "AFSA01H3": [],
    "PHC489Y1": [],
    "WGS419H5": [],
    "IDSB07H3": [],
    "ARC112H1": [],
    "AFSB51H3": [],
    "MGT355H5": [],
    "VPSB77H3": [],
    "EAS241H1": [],
    "HISC04H3": [],
    "MIE315H1": [],
    "BIO304H5": [],
    "SOC240H1": [],
    "SOC447H5": [],
    "MIN450H1": [],
    "FSC220H5": [],
    "PSYC03H3": [],
    "ENGC89H3": [],
    "DRE370H5": [],
    "CIV519H1": [],
    "PMA495Y1": [],
    "WGS430H5": [],
    "THRC56H3": [],
    "ENGC75H3": [],
    "FRE400H5": [],
    "CCT411H5": [],
    "LGGA75H3": [],
    "CLA361H5": [],
    "RLG440H5": [],
    "HISB14H3": [],
    "WSTB13H3": [],
    "CCT454H5": [],
    "HIS230H5": [],
    "FRE488H5": [],
    "ANT216H5": [],
    "ECE221H1": [],
    "ANT204H5": [],
    "ITA450H5": [],
    "ENGC10H3": [],
    "SOC357H5": [],
    "JEG417Y5": [],
    "JOUC18H3": [],
    "ENGB39H3": [],
    "MATA67H3": [],
    "CSC477H5": [],
    "DTS390H1": [],
    "ERS301H5": [],
    "VPSC55H3": [],
    "FREA96H3": [],
    "FREA99H3": [],
    "BIO209H5": [],
    "CCT472H5": [],
    "ITA494H5": [],
    "ECO200Y1": [],
    "SOC326H5": [],
    "STAB52H3": [],
    "SOC363H1": [],
    "MGED91H3": [],
    "CIN305H5": [],
    "CLAC02H3": [],
    "PSYC23H3": [],
    "PLIC54H3": [],
    "HIS498H1": [],
    "GGRC30H3": [],
    "DRS222H5": [],
    "EMU268H1": [],
    "CLAB06H3": [],
    "ERS412H5": [],
    "HIS342H1": [],
    "PHYD57H3": [],
    "GGR277H5": [],
    "MGT430H5": [],
    "ENGA10H3": [],
    "EMU480H1": [],
    "ECO200Y5": [],
    "ECE295H1": [],
    "PHY205H1": [],
    "ANTC31H3": [],
    "MGT437H5": [],
    "ENG374H5": [],
    "CCT221H5": [],
    "ARC452H1": [],
    "JRE410H1": [],
    "HPS250H1": [],
    "GASD01H3": [],
    "PHY250H1": [],
    "THRB40H3": [],
    "HISB41H3": [],
    "PSY490H5": [],
    "HIS107H5": [],
    "VIS301H1": [],
    "STAD37H3": [],
    "MAT395H1": [],
    "CCT286H5": [],
    "CHMD39H3": [],
    "MAT305H5": [],
    "EEB499Y1": [],
    "SOC493H5": [],
    "CCT423H5": [],
    "BIOC21H3": [],
    "NROD61H3": [],
    "LAT213H5": [],
    "PCL472Y1": [],
    "ENGC15H3": [],
    "MGHD25H3": [],
    "BIOC23H3": [],
    "WGS355H1": [],
    "BCB430Y1": [],
    "SOCD44H3": [],
    "STA305H1": [],
    "TMU211Y1": [],
    "TEP442H1": [],
    "COPB51H3": [],
    "ERS299Y5": [],
    "ENGD31H3": [],
    "RLGA02H3": [],
    "STA497H1": [],
    "RLG312Y5": [],
    "SOCD01H3": [],
    "VPSD55H3": [],
    "FSL105H5": [],
    "ECE427H1": [],
    "ECE201H1": [],
    "CLA387H1": [],
    "WRI391H5": [],
    "MIE270H1": [],
    "JMU420H1": [],
    "ENGD14H3": [],
    "JOUC13H3": [],
    "VPHC45H3": [],
    "PSY405H5": [],
    "EDS345H5": [],
    "BIO202H5": [],
    "APS164H1": [],
    "EESB15H3": [],
    "ESC194H1": [],
    "HISC10H3": [],
    "CCT311H5": [],
    "ENGD98Y3": [],
    "STA304H5": [],
    "GGRC50H3": [],
    "FSL121Y1": [],
    "GGR316H5": [],
    "ENG238H5": [],
    "GGRB18H3": [],
    "ERS201H5": [],
    "PMU205Y1": [],
    "PHLD86H3": [],
    "MUZB81H3": [],
    "PHLD36H3": [],
    "MDSC35H3": [],
    "VPHC41H3": [],
    "DRE344H5": [],
    "MGEA02H3": [],
    "CHE391H1": [],
    "PMU463Y1": [],
    "SOC345H5": [],
    "PSY440H5": [],
    "SOC384H5": [],
    "JBH471H5": [],
    "MGAB03H3": [],
    "POL373H1": [],
    "PSYD15H3": [],
    "BIO330H5": [],
    "VPSB67H3": [],
    "FRE181H5": [],
    "CHE354H1": [],
    "ANTC99H3": [],
    "EMU425H1": [],
    "MATA32H3": [],
    "HIS409H5": [],
    "PHL241H5": [],
    "HMB450H1": [],
    "CHM120H5": [],
    "ESTD18H3": [],
    "MGT438H5": [],
    "MUZC42H3": [],
    "CCT460H5": [],
    "MGAC70H3": [],
    "EMU431H1": [],
    "FRE241H5": [],
    "AER525H1": [],
    "CIN101H5": [],
    "ARA300Y5": [],
    "BIOD67H3": [],
    "SOC444H5": [],
    "BIOB99H3": [],
    "GGR329H5": [],
    "RLG411H5": [],
    "MSE298H1": [],
    "SOC324H5": [],
    "CCT431H5": [],
    "SOC463H1": [],
    "ENG110Y1": [],
    "ECO208Y5": [],
    "CSCC37H3": [],
    "STA299Y1": [],
    "APS100H1": [],
    "CHM362H5": [],
    "CCT333H5": [],
    "PMU325Y1": [],
    "PSY312H5": [],
    "EAS340H1": [],
    "MGT120H5": [],
    "AST222H5": [],
    "ITA309H5": [],
    "MGOD30H3": [],
    "JRE420H1": [],
    "ANT322H5": [],
    "CCT320H5": [],
    "STAD95H3": [],
    "ESTC36H3": [],
    "MAT290H1": [],
    "GRK212H5": [],
    "PMU352Y1": [],
    "ECE454H1": [],
    "CLA101H5": [],
    "ECE444H1": [],
    "AER302H1": [],
    "PSY406H5": [],
    "GGRD30H3": [],
    "SPA100Y5": [],
    "PMA452Y1": [],
    "PHLC09H3": [],
    "HIS236H5": [],
    "RLG101H1": [],
    "FREC48H3": [],
    "BIO443H5": [],
    "CITC15H3": [],
    "JAV101H1": [],
    "GGRD14H3": [],
    "EAS256H1": [],
    "ANT398Y0": [],
    "JAL355H5": [],
    "FREB46H3": [],
    "COPA85Y3": [],
    "ECO324H5": [],
    "ENGC23H3": [],
    "WGS301H5": [],
    "PSY341H5": [],
    "ANTC52H3": [],
    "ENV201H5": [],
    "MGED90H3": [],
    "ITA352H5": [],
    "HLTD21H3": [],
    "ENGB27H3": [],
    "LIN318H5": [],
    "LIN399Y1": [],
    "HIN312H5": [],
    "TMU240Y1": [],
    "ARC465H1": [],
    "POL216H5": [],
    "ECE361H1": [],
    "PMA489Y1": [],
    "CHE311H1": [],
    "ESS205H1": [],
    "ECE411H1": [],
    "PMU492Y1": [],
    "ITA255Y5": [],
    "PSYD17H3": [],
    "CCT356H5": [],
    "CSC485H1": [],
    "HISB57H3": [],
    "SOC303H5": [],
    "CSB399Y1": [],
    "EAS314H1": [],
    "ENG255H5": [],
    "ITA370H5": [],
    "CHI409H5": [],
    "SOC486H1": [],
    "WGS370H5": [],
    "COPB13H3": [],
    "ARA410H5": [],
    "EESA07H3": [],
    "MUZB40H3": [],
    "HISB52H3": [],
    "PEY200Y5": [],
    "STA315H5": [],
    "TEP325H1": [],
    "MSE302H1": [],
    "ACMC01H3": [],
    "POLC69H3": [],
    "PMU476Y1": [],
    "HLTC17H3": [],
    "CME261H1": [],
    "PSY352H5": [],
    "SOC349H5": [],
    "PSY320H1": [],
    "SOC345H1": [],
    "CCT321H5": [],
    "ENG390Y5": [],
    "CJS390H1": [],
    "BIOC35H3": [],
    "CLA234H5": [],
    "NROC63H3": [],
    "EESA06H3": [],
    "SOC495H1": [],
    "MSE440H1": [],
    "EDS310H5": [],
    "CSB331H1": [],
    "MGEC62H3": [],
    "ITA420H5": [],
    "POL112H5": [],
    "RLG435H5": [],
    "ARH306Y0": [],
    "SPA275H5": [],
    "ITA272H5": [],
    "PHLC20H3": [],
    "LINB60H3": [],
    "CHE403H1": [],
    "ECO364H5": [],
    "BIO341H5": [],
    "PMA405Y1": [],
    "VPAB17H3": [],
    "FAH399Y5": [],
    "ITA400Y5": [],
    "INS200H1": [],
    "SOCC40H3": [],
    "LIN232H5": [],
    "LIN232H1": [],
    "ENV393H5": [],
    "CSCD03H3": [],
    "PMDB22H3": [],
    "MGT463H5": [],
    "CSC309H1": [],
    "OMU708H1": [],
    "PMU484Y1": [],
    "MGSD01H3": [],
    "CHE562H1": [],
    "POL200Y1": [],
    "SOC391H5": [],
    "MATB42H3": [],
    "TMU318H1": [],
    "ANT203H5": [],
    "PMA463Y1": [],
    "FSC330H5": [],
    "DRS326H5": [],
    "CHMD69H3": [],
    "PHY426H5": [],
    "PSY280H1": [],
    "CSC301H1": [],
    "FSC351H5": [],
    "GGRC32H3": [],
    "CHE113H1": [],
    "PSYC52H3": [],
    "POLC87H3": [],
    "SOCC24H3": [],
    "GGR363H5": [],
    "BIOB38H3": [],
    "SOCD11H3": [],
    "APS502H1": [],
    "PPGB66H3": [],
    "SPA320Y5": [],
    "MUZD80H3": [],
    "MDSD02H3": [],
    "MUZC66H3": [],
    "NMC278H1": [],
    "JEG400Y5": [],
    "EMU456Y1": [],
    "ESS234H0": [],
    "OMU501Y1": [],
    "SOCC58H3": [],
    "CRI427H1": [],
    "MGFD50H3": [],
    "PSYC39H3": [],
    "HLTC20H3": [],
    "MGT220H5": [],
    "PHY478H1": [],
    "IRE260H1": [],
    "PHLB33H3": [],
    "FAH216H5": [],
    "FAS343Y5": [],
    "EDS285H5": [],
    "BIO208H5": [],
    "ERS399Y5": [],
    "HMB442H1": [],
    "ITA235H5": [],
    "TMU310Y1": [],
    "MGSB22H3": [],
    "LIN476H5": [],
    "PMU451Y1": [],
    "ARC487Y1": [],
    "MGT354H5": [],
    "ITA413Y5": [],
    "PSYC51H3": [],
    "ANTC12H3": [],
    "TMU115H1": [],
    "ARC200H1": [],
    "POLC33H3": [],
    "MGFC10H3": [],
    "BME358H1": [],
    "SOC344H5": [],
    "FRE417H5": [],
    "SOC332H5": [],
    "RLG351H5": [],
    "PMU288Y1": [],
    "FRE378H5": [],
    "MIN351H1": [],
    "FAH289H5": [],
    "BME205H1": [],
    "CCT354H5": [],
    "IRE347H1": [],
    "MUZC65H3": [],
    "ENGD96H3": [],
    "CCT401H5": [],
    "PLIC55H3": [],
    "PSYD59H3": [],
    "PMU385Y1": [],
    "CSC373H1": [],
    "COPA89Y3": [],
    "EMU207Y1": [],
    "TEP321H1": [],
    "PHY351H5": [],
    "PSY399H5": [],
    "STA313H5": [],
    "MIE469H1": [],
    "BIOC52H3": [],
    "SOC348H5": [],
    "MGT399Y5": [],
    "SOC220H1": [],
    "MUZC64H3": [],
    "PHY399Y5": [],
    "LAT202H1": [],
    "CIN205H5": [],
    "EMU356Y1": [],
    "ANT102H5": [],
    "CHM110H5": [],
    "FSL466H5": [],
    "POL438H1": [],
    "MGAC03H3": [],
    "PHS300H1": [],
    "MAT132H5": [],
    "MDSA01H3": [],
    "HIS315H5": [],
    "MATD11H3": [],
    "IDSC04H3": [],
    "ARC366H1": [],
    "POL402H5": [],
    "WGS367H5": [],
    "CSCC10H3": [],
    "PMA479Y1": [],
    "ENV430H5": [],
    "CHI204H5": [],
    "POLC80H3": [],
    "WGS373H1": [],
    "SOC375H5": [],
    "MGT270H5": [],
    "MGED50H3": [],
    "PHY252H1": [],
    "PMU262H1": [],
    "ECE326H1": [],
    "MSE401H1": [],
    "OMU602Y1": [],
    "SOC370H1": [],
    "STA360H5": [],
    "CIV220H1": [],
    "OMU611H1": [],
    "MAT344H1": [],
    "HST209H1": [],
    "AER510H1": [],
    "MAT337H5": [],
    "PMU412H1": [],
    "MGFD70H3": [],
    "POL391H5": [],
    "CHE568H1": [],
    "FREC01H3": [],
    "MGHB02H3": [],
    "CDN221H1": [],
    "LIN498H5": [],
    "CIV102H1": [],
    "ENG343H5": [],
    "SOCB70H3": [],
    "MIE344H1": [],
    "RLG303H5": [],
    "CCT480H5": [],
    "APS105H1": [],
    "MGT260H5": [],
    "MGEB12H3": [],
    "MUZB67H3": [],
    "CCT341H5": [],
    "BIOC10H3": [],
    "GGR278H5": [],
    "STA498H5": [],
    "FRED28H3": [],
    "PSY270H1": [],
    "MGEC40H3": [],
    "ESS410H1": [],
    "PEY500H1": [],
    "PHL332H5": [],
    "GGRC13H3": [],
    "GGR111H5": [],
    "ENGC12H3": [],
    "INS496H1": [],
    "MIE491Y1": [],
    "MGEC08H3": [],
    "STA220H5": [],
    "MGSC14H3": [],
    "APS110H1": [],
    "ROB498H1": [],
    "POL486H1": [],
    "POL317H1": [],
    "AST101H1": [],
    "CHMA10H3": [],
    "MGEC06H3": [],
    "MGFD60H3": [],
    "RLG387H1": [],
    "GGR318H5": [],
    "BCB330Y1": [],
    "TMU309H1": [],
    "PMU291Y1": [],
    "CIV510H1": [],
    "ERS303H5": [],
    "ITA237H5": [],
    "PSY346H5": [],
    "ECO205Y5": [],
    "PMU400Y1": [],
    "EDS100H5": [],
    "PSYD98Y3": [],
    "CSC108H1": [],
    "ENGD94H3": [],
    "CSC338H5": [],
    "HLTD25H3": [],
    "MGD415H5": [],
    "HIS221H5": [],
    "CSC263H1": [],
    "LINB62H3": [],
    "GGR406H5": [],
    "LINB04H3": [],
    "MGMC13H3": [],
    "PSY274H5": [],
    "CSC309H5": [],
    "PSYC53H3": [],
    "ARC365H1": [],
    "PLID56H3": [],
    "ROB501H1": [],
    "ARC453H1": [],
    "HLTC25H3": [],
    "BIO400Y5": [],
    "PSY202H1": [],
    "RLG465H5": [],
    "ENV100Y5": [],
    "CCT371H5": [],
    "FRE272Y5": [],
    "ECO209Y5": [],
    "ANTB36H3": [],
    "ANT399H5": [],
    "ARC353H1": [],
    "CRI340H1": [],
    "CIV420H1": [],
    "CCT273H5": [],
    "MGT414H5": [],
    "RLG317H5": [],
    "SOC318H5": [],
    "PMA440Y1": [],
    "CCT226H5": [],
    "ITA242H5": [],
    "ECE520H1": [],
    "ESS105H1": [],
    "EAS274H1": [],
    "SPA259H5": [],
    "COPA30Y3": [],
    "VPSC66H3": [],
    "FREB28H3": [],
    "PMA436Y1": [],
    "VPAA10H3": [],
    "ERS211H5": [],
    "SOC387H5": [],
    "MGHD14H3": [],
    "HLTC42H3": [],
    "PMU384H1": [],
    "WRI370H5": [],
    "BIOC13H3": [],
    "ECO399H5": [],
    "THRD55H3": [],
    "PHYD38H3": [],
    "EESD09H3": [],
    "FAH494H5": [],
    "FRE210H1": [],
    "MIE488H1": [],
    "ARC461H1": [],
    "GGR252H5": [],
    "MAT134H5": [],
    "BIOC19H3": [],
    "ANT497Y1": [],
    "MSE431H1": [],
    "BIOD96Y3": [],
    "IDSC11H3": [],
    "MATD12H3": [],
    "BIO407H5": [],
    "CSC324H1": [],
    "PHL210Y1": [],
    "HIS262H5": [],
    "PMU287Y1": [],
    "CHI211H5": [],
    "MIN225H1": [],
    "ANTD40H3": [],
    "GER391H1": [],
    "ANTC61H3": [],
    "MAT244H5": [],
    "HMB399Y1": [],
    "FAS451H5": [],
    "ITA233H5": [],
    "MAT233H5": [],
    "EAS271H1": [],
    "SOC399Y5": [],
    "CCT224H5": [],
    "SPA219Y5": [],
    "FSC406H5": [],
    "PHYB57H3": [],
    "CME499H1": [],
    "ANT337H5": [],
    "ANA498Y1": [],
    "TMU403H1": [],
    "ANA300Y1": [],
    "MGFB10H3": [],
    "ENGC50H3": [],
    "ANT399Y5": [],
    "PMU315Y1": [],
    "MUZB60H3": [],
    "ENG202H1": [],
    "PMA394Y1": [],
    "CCT373H5": [],
    "COPB31H3": [],
    "BCH299Y1": [],
    "SOC216H5": [],
    "HIS241H1": [],
    "SOC322H5": [],
    "ANT407H5": [],
    "MSE244H1": [],
    "CSB498Y1": [],
    "ANT217H5": [],
    "SDS459Y1": [],
    "JEP452H5": [],
    "ECTD68H3": [],
    "ANT201H5": [],
    "SOC310H5": [],
    "FAS346Y5": [],
    "ANTC34H3": [],
    "HSC200H5": [],
    "CCT403H5": [],
    "POLD87H3": [],
    "CITC12H3": [],
    "ENGB52H3": [],
    "OMU741Y1": [],
    "MATA23H3": [],
    "URD212Y5": [],
    "CSCB09H3": [],
    "ENGB04H3": [],
    "MIE440H1": [],
    "TEP320H1": [],
    "FAH492H5": [],
    "ENGB61H3": [],
    "BIO312H5": [],
    "ENGD71H3": [],
    "JOUB01H3": [],
    "CCT499Y5": [],
    "HIS210H5": [],
    "CHE204H1": [],
    "FREB50H3": [],
    "CHMB23H3": [],
    "VIS218H1": [],
    "HSC300H5": [],
    "LIN340H5": [],
    "MIE444H1": [],
    "MAT388H5": [],
    "FSC399Y5": [],
    "CSC499Y5": [],
    "ERS312H5": [],
    "FRE369H5": [],
    "PSYC16H3": [],
    "ECO227Y5": [],
    "CSB329H1": [],
    "MIE515H1": [],
    "SOC406H5": [],
    "ITA312H1": [],
    "TMU105Y1": [],
    "PSY336H1": [],
    "CRI391H1": [],
    "GRK211H5": [],
    "ANT300H5": [],
    "ECO320H1": [],
    "MIE459H1": [],
    "MGSC03H3": [],
    "ENG300Y5": [],
    "CSCD54H3": [],
    "ENG472H5": [],
    "ECE367H1": [],
    "MDSB25H3": [],
    "EMU485H1": [],
    "CHE299H1": [],
    "HLTB11H3": [],
    "POL309Y5": [],
    "MUZC67H3": [],
    "HISC01H3": [],
    "FSC307H5": [],
    "DRE346H5": [],
    "ENV299Y1": [],
    "CHE430Y1": [],
    "CHI104H5": [],
    "ESTB01H3": [],
    "CSC258H5": [],
    "EMU154H1": [],
    "ECO335H5": [],
    "CHM399Y1": [],
    "CPS400Y5": [],
    "STA261H1": [],
    "MIE506H1": [],
    "FLDD01H3": [],
    "VPSB59H3": [],
    "IRE244H1": [],
    "MUS210H1": [],
    "CHE460H1": [],
    "MMU201H1": [],
    "ENG385H5": [],
    "MIN250H1": [],
    "SOC275H5": [],
    "MAT137Y5": [],
    "MIN330H1": [],
    "MUS306H1": [],
    "PHLD78H3": [],
    "ANTB26H3": [],
    "LIND29H3": [],
    "MSE458H1": [],
    "PLID74H3": [],
    "RSM332H1": [],
    "MGTD81H3": [],
    "TEP324H1": [],
    "STA304H1": [],
    "GGR437H5": [],
    "BIO200H5": [],
    "CJS340H1": [],
    "ARC354H1": [],
    "RSM435H1": [],
    "HISD44H3": [],
    "BIO206H5": [],
    "CSC236H5": [],
    "HIS480H5": [],
    "TMU111H1": [],
    "WGS353H5": [],
    "HISD32H3": [],
    "PMU095H1": [],
    "HIS213H5": [],
    "BME460H1": [],
    "MGMC14H3": [],
    "POLC56H3": [],
    "PSY322H1": [],
    "ECO102H1": [],
    "PHLB13H3": [],
    "CHE375H1": [],
    "HIS367H5": [],
    "CCT384H5": [],
    "ACMB01H3": [],
    "MAT244H1": [],
    "UTM103H5": [],
    "SOC423H5": [],
    "PSY329H5": [],
    "PSY442Y5": [],
    "DRE342H5": [],
    "AST252H5": [],
    "LIN329H5": [],
    "JPE251H5": [],
    "HPS283H1": [],
    "CSC488H5": [],
    "FSC316H5": [],
    "VCC392H5": [],
    "BIO376H5": [],
    "MUZC61H3": [],
    "CSCA48H3": [],
    "PSY100H1": [],
    "PSYD52H3": [],
    "MGT417H5": [],
    "FLDD02H3": [],
    "ANT498H1": [],
    "BIO411H5": [],
    "HLTC49H3": [],
    "ACT496H1": [],
    "CLA388H1": [],
    "PSYB57H3": [],
    "ECO436H5": [],
    "ECE470H1": [],
    "SOC354H1": [],
    "ARC253H1": [],
    "ITA200Y5": [],
    "CHE399H1": [],
    "MGTD80H3": [],
    "BIO203H5": [],
    "GGRB32H3": [],
    "ECO100Y5": [],
    "CSB497H1": [],
    "ARA312Y5": [],
    "WGS205H5": [],
    "RLG302H5": [],
    "ECO435H5": [],
    "STA255H1": [],
    "OMU506Y1": [],
    "ECO208Y1": [],
    "POL303Y5": [],
    "FREB45H3": [],
    "BIO414H5": [],
    "HISB10H3": [],
    "BIOB50H3": [],
    "LIN385H5": [],
    "SOC392H1": [],
    "SOC209H1": [],
    "ENGD28Y3": [],
    "ECE212H1": [],
    "POLD41H3": [],
    "VPSC68H3": [],
    "WGS336H5": [],
    "VPSB88H3": [],
    "CIV440H1": [],
    "PHY136H5": [],
    "PMU268Y1": [],
    "FRED01H3": [],
    "APS360H1": [],
    "MGFC20H3": [],
    "CHE322H1": [],
    "PLID01H3": [],
    "ITA489H1": [],
    "COPC98H3": [],
    "FAS445Y5": [],
    "TMU107Y1": [],
    "CHE561H1": [],
    "STA398H5": [],
    "MAT492H5": [],
    "PMU267Y1": [],
    "SOC211H5": [],
    "MDSB09H3": [],
    "PSY310H5": [],
    "POLC37H3": [],
    "MSE437H1": [],
    "MGD421H5": [],
    "MIE240H1": [],
    "RSM333H1": [],
    "LGGA61H3": [],
    "SOC301H5": [],
    "EEB215H1": [],
    "EMU360H1": [],
    "ESS103H1": [],
    "HIS282H5": [],
    "USA495Y1": [],
    "TEP322H1": [],
    "WGS421H5": [],
    "FAH346H1": [],
    "PHL367H5": [],
    "MGIC01H3": [],
    "MIE490Y1": [],
    "PHL243H5": [],
    "STA221H5": [],
    "LINB09H3": [],
    "POL380H1": [],
    "MAT367H1": [],
    "BCH472Y1": [],
    "MATB24H3": [],
    "CHE334H1": [],
    "UTM102H5": [],
    "LGGC63H3": [],
    "MGY277H1": [],
    "PMU292Y1": [],
    "APS510H1": [],
    "GASC73H3": [],
    "AFSD53H3": [],
    "ANTB22H3": [],
    "GGR321H5": [],
    "MUZB01H3": [],
    "THRD60H3": [],
    "IMI400H5": [],
    "FRE442H5": [],
    "MAT133Y5": [],
    "VPAC17H3": [],
    "PMDB32Y3": [],
    "MIE342H1": [],
    "ANT369H5": [],
    "TEP234H1": [],
    "GGR202H5": [],
    "CCT336H5": [],
    "SOC415H5": [],
    "MUZA64H3": [],
    "BIO375H5": [],
    "PSYD35H3": [],
    "MGY299Y1": [],
    "IDSC17H3": [],
    "SOC208H5": [],
    "TMU112H1": [],
    "HMB394Y0": [],
    "ACMB10H3": [],
    "ANTB35H3": [],
    "EDS399H5": [],
    "ECO351H1": [],
    "CLAC94H3": [],
    "PSYB30H3": [],
    "PHL243H1": [],
    "ENG371H1": [],
    "POL369Y5": [],
    "BIOD59H3": [],
    "PHLD89Y3": [],
    "OMU720Y1": [],
    "SOC204H1": [],
    "CIN401H5": [],
    "WGS102H5": [],
    "VCC292H5": [],
    "POLC97H3": [],
    "CHE220H1": [],
    "ANTC62H3": [],
    "HIS323H5": [],
    "ECO461H5": [],
    "MSE490H1": [],
    "PHL489Y5": [],
    "FRED02H3": [],
    "ARC462Y1": [],
    "MATB44H3": [],
    "ROB301H1": [],
    "CSC363H5": [],
    "CIV517H1": [],
    "ECO358H1": [],
    "ANT460H5": [],
    "ARA408H5": [],
    "PSYC85H3": [],
    "ECE243H1": [],
    "SOC326H1": [],
    "HLTD48H3": [],
    "MATB43H3": [],
    "ECE357H1": [],
    "ENG204H5": [],
    "CCT405H5": [],
    "HLTC19H3": [],
    "CIV100H1": [],
    "FREC54H3": [],
    "POL399Y1": [],
    "CME358H1": [],
    "NMC373H1": [],
    "ANT338H5": [],
    "POLA01H3": [],
    "SOC358H5": [],
    "BIOB12H3": [],
    "VPAC22H3": [],
    "PSYD55H3": [],
    "LGGC66H3": [],
    "CHMD11H3": [],
    "ANT335H5": [],
    "PSY391H5": [],
    "NROD60H3": [],
    "DRE347H5": [],
    "TRN399Y1": [],
    "PMU401H1": [],
    "ECE526H1": [],
    "SLA101H1": [],
    "MAT202H5": [],
    "PHLD94H3": [],
    "ECO220Y5": [],
    "GGR304H5": [],
    "AER307H1": [],
    "PEY200H1": [],
    "ENGA03H3": [],
    "MGED06H3": [],
    "STAC51H3": [],
    "ESC384H1": [],
    "CHE451H1": [],
    "ANTD01H3": [],
    "BIO299Y5": [],
    "GASB33H3": [],
    "SOC251H1": [],
    "PMU192Y1": [],
    "HLTD71Y3": [],
    "JOUD12H3": [],
    "BIO368H5": [],
    "VIS318H1": [],
    "SOC214H1": [],
    "MGT491H5": [],
    "TMU301H1": [],
    "HIS261H5": [],
    "CLAA04H3": [],
    "MIE230H1": [],
    "MAT499Y5": [],
    "PHL327H5": [],
    "AFSB50H3": [],
    "HIS103Y1": [],
    "STAC62H3": [],
    "FREB27H3": [],
    "PSYB51H3": [],
    "MIE369H1": [],
    "BIOD60H3": [],
    "VPSC53H3": [],
    "CSCB63H3": [],
    "AFSD51H3": [],
    "STA478H5": [],
    "ECE350H1": [],
    "CLA404H5": [],
    "AER407H1": [],
    "OMU605H1": [],
    "ENV299Y5": [],
    "PLID02H3": [],
    "PHY207H1": [],
    "MAT387H5": [],
    "ECE352H1": [],
    "JCP221H5": [],
    "WGS365H5": [],
    "FAH380H1": [],
    "MIE210H1": [],
    "WSTD10H3": [],
    "MIE304H1": [],
    "FRED04H3": [],
    "CCT109H5": [],
    "PSY311H5": [],
    "ECO202Y5": [],
    "PSY420H5": [],
    "POLB30H3": [],
    "MAT354H5": [],
    "THRB22H3": [],
    "GGR227H5": [],
    "FAS434Y5": [],
    "ANTB64H3": [],
    "HISA06H3": [],
    "MSE493H1": [],
    "GGR272H1": [],
    "LGGD66H3": [],
    "AER503H1": [],
    "ARC362Y1": [],
    "EESB20H3": [],
    "JMU303H1": [],
    "FRE240H5": [],
    "BIO372H5": [],
    "MGSC01H3": [],
    "ARC351H1": [],
    "BIO481Y5": [],
    "ARC380Y1": [],
    "PMA445Y1": [],
    "POLC68H3": [],
    "EESD18H3": [],
    "CCT219H5": [],
    "VPAB16H3": [],
    "PSY355H5": [],
    "JGE378H5": [],
    "CITD01H3": [],
    "ERS411H5": [],
    "PSY319H5": [],
    "SOCD25H3": [],
    "MATD93H3": [],
    "ITA491Y5": [],
    "PMA482Y1": [],
    "VPSB62H3": [],
    "ESC103H1": [],
    "MAT309H5": [],
    "APS530H1": [],
    "GASD55H3": [],
    "PMU355Y1": [],
    "HIS103H5": [],
    "HSC406H5": [],
    "ITA310H1": [],
    "ESTC35H3": [],
    "MDSD01H3": [],
    "LAT212H5": [],
    "LIN337H5": [],
    "CLA207H5": [],
    "ECE464H1": [],
    "ENG105H5": [],
    "PHLA10H3": [],
    "SOC210H1": [],
    "ENG312H5": [],
    "ENGB70H3": [],
    "PMU485Y1": [],
    "CSC347H5": [],
    "ARC399Y1": [],
    "ANTD10H3": [],
    "PSYA01H3": [],
    "CHM373H5": [],
    "SOC387H1": [],
    "PHLD20H3": [],
    "SOC293H1": [],
    "FAH317H5": [],
    "GGRB03H3": [],
    "POLC79H3": [],
    "ENV491Y1": [],
    "MGT299Y5": [],
    "CSC263H5": [],
    "MIE438H1": [],
    "MUZC41H3": [],
    "EMU256H1": [],
    "VIS328H1": [],
    "SOC391H1": [],
    "ANTC15H3": [],
    "PHL315H5": [],
    "DTS401H5": [],
    "CHI311H5": [],
    "MGT363H5": [],
    "PHY100H1": [],
    "EESD10Y3": [],
    "LINA01H3": [],
    "COPA96Y3": [],
    "MGT412H5": [],
    "OMU620Y1": [],
    "ENG280H5": [],
    "CCT482H5": [],
    "VPSC51H3": [],
    "MAT232H5": [],
    "ARA411H5": [],
    "COPA43Y3": [],
    "PSYD23H3": [],
    "CLA399Y5": [],
    "ENGC39H3": [],
    "CLA201H5": [],
    "HMU345H1": [],
    "CHE230H1": [],
    "STAB22H3": [],
    "MUZB62H3": [],
    "CSCB20H3": [],
    "DRE200H5": [],
    "FSC360H5": [],
    "BME595H1": [],
    "EMU370Y1": [],
    "LINB98H3": [],
    "POL218Y5": [],
    "STAB27H3": [],
    "CLAC11H3": [],
    "MAT406H5": [],
    "CHI304H5": [],
    "JFL389H5": [],
    "GGR426H5": [],
    "SOC493H1": [],
    "LIN497Y1": [],
    "PMU382Y1": [],
    "LIN310H5": [],
    "NROD67H3": [],
    "MAT396H1": [],
    "MGMC02H3": [],
    "GGR112H5": [],
    "PMU272Y1": [],
    "CITC04H3": [],
    "PSY430H5": [],
    "HMB420H1": [],
    "CIV282H1": [],
    "JMU184Y1": [],
    "PHL275H1": [],
    "WSTA01H3": [],
    "GGRC15H3": [],
    "CHI410H5": [],
    "HISD14H3": [],
    "ECE191H1": [],
    "MGT312H5": [],
    "CME210H1": [],
    "ENGC20H3": [],
    "CHE260H1": [],
    "ENG365H5": [],
    "CHM399Y5": [],
    "ANTB18H3": [],
    "SOC346H5": [],
    "WRI395H5": [],
    "VIS410H1": [],
    "PSY230H1": [],
    "HMU430H1": [],
    "EDS377H5": [],
    "ERS302H5": [],
    "HLTD07H3": [],
    "ENG399Y5": [],
    "JOUC80H3": [],
    "ASTB23H3": [],
    "CSC490H5": [],
    "CSCA67H3": [],
    "COPA88Y3": [],
    "DTS201H5": [],
    "CITB08H3": [],
    "NMEB05H3": [],
    "LIN299Y5": [],
    "HISC36H3": [],
    "VIS302H1": [],
    "HIS385H5": [],
    "CHM331H5": [],
    "IMI301H5": [],
    "FAH102H1": [],
    "PHYB56H3": [],
    "CCT111H5": [],
    "CSC392H5": [],
    "OMU622Y1": [],
    "ANTD16H3": [],
    "BIO230H1": [],
    "MGT429H5": [],
    "NMC102H1": [],
    "MAT224H1": [],
    "ESS450H0": [],
    "VPSC79H3": [],
    "BME455H1": [],
    "HPS300H1": [],
    "MGSD40H3": [],
    "CHE223H1": [],
    "AFSB01H3": [],
    "PMA494Y1": [],
    "HIS295H5": [],
    "ACMB02H3": [],
    "LIN200H1": [],
    "SOC347H5": [],
    "SOCC29H3": [],
    "CCT285H5": [],
    "ERS471H5": [],
    "STA305H5": [],
    "HMB342H1": [],
    "BIO356H5": [],
    "THRB55H3": [],
    "MGIB12H3": [],
    "GASC33H3": [],
    "WSTC02H3": [],
    "BCH210H1": [],
    "PHYB52H3": [],
    "RLG299Y5": [],
    "ANT367H5": [],
    "JMU100Y1": [],
    "FAH291H5": [],
    "ECO421H1": [],
    "BCH399Y1": [],
    "PSYC71H3": [],
    "ECTC62H3": [],
    "PHL314H5": [],
    "SOCB58H3": [],
    "OMU508H1": [],
    "POL496H1": [],
    "ENG400H5": [],
    "SOC339H5": [],
    "GGR209H5": [],
    "WGS434H5": [],
    "MGT321H5": [],
    "FAS334Y5": [],
    "FREC58H3": [],
    "MIE517H1": [],
    "PMU489Y1": [],
    "VST410H5": [],
    "ENV205H5": [],
    "LTL487H5": [],
    "EMU330Y1": [],
    "LIN203H1": [],
    "VIS211H1": [],
    "PHLD93H3": [],
    "VIS405H1": [],
    "MATD26H3": [],
    "BIOC34H3": [],
    "ECO380H1": [],
    "PSY331H5": [],
    "ECE422H1": [],
    "CSC498H5": [],
    "PHL390H5": [],
    "ITA491H5": [],
    "MDSC41H3": [],
    "ANT498H5": [],
    "BIOB51H3": [],
    "CHMB31H3": [],
    "PSYC90H3": [],
    "ENGC43H3": [],
    "PSY384H5": [],
    "APS062H1": [],
    "THRB50H3": [],
    "POLC42H3": [],
    "FRE280Y5": [],
    "WSTB12H3": [],
    "SOC270H1": [],
    "CHMD79H3": [],
    "MGMC11H3": [],
    "PHY324H5": [],
    "SOC480Y5": [],
    "VPSC54H3": [],
    "MUZA65H3": [],
    "POL497H1": [],
    "ANT220H5": [],
    "WSTB11H3": [],
    "FAS246H5": [],
    "ECO411H5": [],
    "ACMD01H3": [],
    "ECO358H5": [],
    "HIS399Y5": [],
    "PHLC37H3": [],
    "GGR339H1": [],
    "CSC318H1": [],
    "PSYD66H3": [],
    "CSC343H5": [],
    "JAV130H1": [],
    "GGRD31H3": [],
    "LIN369H5": [],
    "LIN388H5": [],
    "MIE301H1": [],
    "LIN496H1": [],
    "ANTC18H3": [],
    "EAS394H1": [],
    "PMU270Y1": [],
    "EESB16H3": [],
    "ECO399Y5": [],
    "FAH216H1": [],
    "LGGC64H3": [],
    "MGEB32H3": [],
    "ANT200H5": [],
    "MGM464H5": [],
    "PSY329H1": [],
    "SOCB35H3": [],
    "SAN392Y5": [],
    "BIO339H5": [],
    "MGSD24H3": [],
    "SMC219Y1": [],
    "MATC44H3": [],
    "PMDB30H3": [],
    "MIE424H1": [],
    "EMU461H1": [],
    "VIS325H1": [],
    "RSM324H1": [],
    "CSC258H1": [],
    "WGS347H5": [],
    "MIN320H1": [],
    "HISA07H3": [],
    "ANTD07H3": [],
    "STAC67H3": [],
    "CLA497Y5": [],
    "ARH306Y1": [],
    "POL447H1": [],
    "PHY397Y0": [],
    "GASB58H3": [],
    "ECO460H5": [],
    "BIOD19H3": [],
    "MGHB12H3": [],
    "EMU359H1": [],
    "ECO475H5": [],
    "IDSD02H3": [],
    "ENGB08H3": [],
    "SOC309H1": [],
    "MGT415H5": [],
    "ITA373H5": [],
    "POLD50H3": [],
    "ENGC92H3": [],
    "PHY147H5": [],
    "PMA476Y1": [],
    "HLTD04H3": [],
    "BIOD17H3": [],
    "CLA231H5": [],
    "BIO409H5": [],
    "BIO399Y5": [],
    "PPGD68H3": [],
    "PSY396H1": [],
    "ANT312H5": [],
    "RSM411H1": [],
    "PHLD95H3": [],
    "ANTC20H3": [],
    "CHMC11H3": [],
    "ENG203H5": [],
    "CCT205H5": [],
    "ECO440H5": [],
    "FAS447Y5": [],
    "FAS450Y5": [],
    "NMC277H1": [],
    "ENGC03H3": [],
    "EESD15H3": [],
    "PHL246H5": [],
    "MIE457H1": [],
    "EMU152H1": [],
    "VIS331H1": [],
    "SOC321H5": [],
    "FAS232H5": [],
    "SOC212H1": [],
    "FLDC01H3": [],
    "CCT395H5": [],
    "LINB10H3": [],
    "FRE399Y5": [],
    "CHE205H1": [],
    "CSC409H5": [],
    "HISA05H3": [],
    "ARC399H1": [],
    "PHLB81H3": [],
    "JMU410Y1": [],
    "CLAB05H3": [],
    "LGGB60H3": [],
    "GER200Y1": [],
    "CLA369H5": [],
    "HLTB41H3": [],
    "PMU085H1": [],
    "IDSB04H3": [],
    "ECO313H1": [],
    "PHLC72H3": [],
    "ENGC06H3": [],
    "BIOC20H3": [],
    "POLD89H3": [],
    "PHL282H5": [],
    "CLA201H1": [],
    "FAH315H5": [],
    "RSM403Y1": [],
    "AER301H1": [],
    "CRI205H1": [],
    "VIS322H1": [],
    "MIN511H1": [],
    "JPE252H5": [],
    "ENGC47H3": [],
    "BIO205H5": [],
    "CHE441H1": [],
    "LINC12H3": [],
    "MGT393H5": [],
    "LTL486H5": [],
    "HMB496Y1": [],
    "FREB17H3": [],
    "PHL303H1": [],
    "ENGC09H3": [],
    "VIS431Y1": [],
    "ANT355H5": [],
    "POL203Y5": [],
    "IDSD01Y3": [],
    "MIE311H1": [],
    "CITB03H3": [],
    "PHLB17H3": [],
    "JCP422H5": [],
    "ARC363Y1": [],
    "CIV518H1": [],
    "PHY131H1": [],
    "ESS391H1": [],
    "MAT334H1": [],
    "MUS211H1": [],
    "PHY451H5": [],
    "MGT322H5": [],
    "FRE454H5": [],
    "POLC54H3": [],
    "PHYD26H3": [],
    "THRC40H3": [],
    "ENG381H5": [],
    "CIV375H1": [],
    "BIOC62H3": [],
    "PHY347H5": [],
    "CCT270H5": [],
    "PSY362H5": [],
    "BIOD45H3": [],
    "ENG202H5": [],
    "COPA78Y3": [],
    "CHE467H1": [],
    "PSYB38H3": [],
    "HLTC43H3": [],
    "EMU240H1": [],
    "ESC203H1": [],
    "PMU255Y1": [],
    "HMB422H1": [],
    "FAH448H1": [],
    "BME395H1": [],
    "MGHC02H3": [],
    "MIE567H1": [],
    "PSY340H5": [],
    "VPHC73H3": [],
    "JOUC25H3": [],
    "CME321H1": [],
    "ENGC82H3": [],
    "PHLC05H3": [],
    "EESC37H3": [],
    "FAH279H5": [],
    "PMU228H1": [],
    "MUZC23H3": [],
    "CIN301H5": [],
    "ESC490H1": [],
    "GGR309H5": [],
    "HMB300H1": [],
    "PHLD92H3": [],
    "WSTB10H3": [],
    "OMU505H1": [],
    "MDSC62H3": [],
    "VPSB71H3": [],
    "ANTB19H3": [],
    "SMC451Y1": [],
    "CME500H1": [],
    "IDSA01H3": [],
    "VPHC63H3": [],
    "CLA359H5": [],
    "GGR107H1": [],
    "FSL102H1": [],
    "WRI330H5": [],
    "CCT416H5": [],
    "FAH310H5": [],
    "CSC398H5": [],
    "ENG237H5": [],
    "MGAD50H3": [],
    "CCT208H5": [],
    "FSC210H5": [],
    "OMU502Y1": [],
    "CSC413H5": [],
    "RLG210H5": [],
    "AFSB05H3": [],
    "VPHC53H3": [],
    "ANT206H5": [],
    "LIN101H5": [],
    "LINC47H3": [],
    "ECO101H5": [],
    "PMA135Y1": [],
    "PSYC37H3": [],
    "PHLC14H3": [],
    "PSY393H5": [],
    "LIND02H3": [],
    "ARC482H1": [],
    "TMU410Y1": [],
    "HLTB60H3": [],
    "SOC327H5": [],
    "ENG391Y5": [],
    "PSY100Y5": [],
    "MATD16H3": [],
    "PMU190Y1": [],
    "JEP351H5": [],
    "PHYD72H3": [],
    "RLG332H5": [],
    "JBC472H5": [],
    "CIV575H1": [],
    "EMU499Y1": [],
    "CSC209H5": [],
    "MAT498H5": [],
    "CIN215H5": [],
    "ECE448H1": [],
    "HLTD06H3": [],
    "WGS343H5": [],
    "GGR214H5": [],
    "FRE245H1": [],
    "POLD51H3": [],
    "ECO331H1": [],
    "PMU351Y1": [],
    "ERS403H5": [],
    "STAC70H3": [],
    "BIO374H5": [],
    "WSTB09H3": [],
    "ITA497H5": [],
    "JMU385Y1": [],
    "BIO373H5": [],
    "POL208H1": [],
    "UTM193H5": [],
    "NML110Y1": [],
    "JMU215H1": [],
    "PHLC92H3": [],
    "DRM288H1": [],
    "CIN402H5": [],
    "CIV580H1": [],
    "BIOB10H3": [],
    "CCT433H5": [],
    "BIOA01H3": [],
    "BIOA02H3": [],
    "PMU195Y1": [],
    "POLC38H3": [],
    "MIE442H1": [],
    "BIO417H5": [],
    "ERS111H5": [],
    "FREC47H3": [],
    "COPB12H3": [],
    "CHMC47H3": [],
    "ECO374H1": [],
    "PSYB32H3": [],
    "SOC475H5": [],
    "BIOC17H3": [],
    "OMU503Y1": [],
    "GGR399Y5": [],
    "LIN231H5": [],
    "EDS291H5": [],
    "SOCB43H3": [],
    "ECE568H1": [],
    "CME263H1": [],
    "MAT398H5": [],
    "ANTC32H3": [],
    "TRN404Y1": [],
    "VIS306H1": [],
    "CCT406H5": [],
    "MAT405H5": [],
    "ENG273Y1": [],
    "SOC354H5": [],
    "PMU480Y1": [],
    "NMEB09H3": [],
    "MIE303H1": [],
    "MGT458H5": [],
    "MGT423H5": [],
    "ECE253H1": [],
    "MIE242H1": [],
    "MGT422H5": [],
    "DRE356H5": [],
    "MAT135H1": [],
    "PSYB07H3": [],
    "ENG329H1": [],
    "MAT257Y5": [],
    "GGR361H5": [],
    "BIOD37H3": [],
    "PMDC40H3": [],
    "NROC64H3": [],
    "CSC384H5": [],
    "LINB20H3": [],
    "DRS122H5": [],
    "PSY403H5": [],
    "OMU702Y1": [],
    "WSTC66H3": [],
    "MGEC11H3": [],
    "FSL106H5": [],
    "PHL221H5": [],
    "MIE523H1": [],
    "SOC224H5": [],
    "JLP315H1": [],
    "PLID03H3": [],
    "ACT370H1": [],
    "BIOB90H3": [],
    "INS201Y1": [],
    "ISP100H5": [],
    "PMU436Y1": [],
    "TMU130H1": [],
    "WGS435Y5": [],
    "PSY354H5": [],
    "PHLC93H3": [],
    "PHY294H1": [],
    "MGT325H5": [],
    "MATC27H3": [],
    "MMU200H1": [],
    "VCC490H5": [],
    "HIS388H5": [],
    "SOC381H1": [],
    "GGRC25H3": [],
    "VIS421H1": [],
    "TMU210Y1": [],
    "FSL221Y1": [],
    "RLG207H5": [],
    "FAS453H5": [],
    "WGS397H1": [],
    "TMU404H1": [],
    "VPHD42Y3": [],
    "MGFD10H3": [],
    "MGT461H5": [],
    "SOC109H5": [],
    "MGEB05H3": [],
    "SOC407H5": [],
    "PHLD09H3": [],
    "MGFC60H3": [],
    "HLTD27H3": [],
    "CCT424H5": [],
    "JOUD10H3": [],
    "PMU383Y1": [],
    "ECE110H1": [],
    "POL377H1": [],
    "JCP463H5": [],
    "CSB353H1": [],
    "MAT488H5": [],
    "TMU411H1": [],
    "FSC239Y5": [],
    "CLA321H1": [],
    "ENG101H5": [],
    "GGRD08H3": [],
    "ENGB34H3": [],
    "ANT381H5": [],
    "FREA98H3": [],
    "PSYB55H3": [],
    "ENG367H5": [],
    "CCT112H5": [],
    "CSC495H1": [],
    "DRE420H5": [],
    "CIN490Y1": [],
    "CRI490H1": [],
    "MATA37H3": [],
    "ENG100H1": [],
    "PCL297H1": [],
    "PSY201H5": [],
    "FREB08H3": [],
    "IMI303H5": [],
    "ENV496H5": [],
    "HISD48H3": [],
    "MUZB61H3": [],
    "ANTB14H3": [],
    "BIO270H1": [],
    "MSE301H1": [],
    "PMU378Y1": [],
    "ENGC42H3": [],
    "BIO130H1": [],
    "RLG499H5": [],
    "THRB30H3": [],
    "MSE218H1": [],
    "AER303H1": [],
    "SDS470H1": [],
    "MGHD28H3": [],
    "COPA95Y3": [],
    "PHLD97H3": [],
    "MIE191H1": [],
    "PHL333H5": [],
    "ERS101H5": [],
    "CCT310H5": [],
    "BIO483H5": [],
    "SOC206H5": [],
    "CHMD71H3": [],
    "PHY245H5": [],
    "RLG361H5": [],
    "MAT223H1": [],
    "SMU401H1": [],
    "ITA374H5": [],
    "HIS201H5": [],
    "MGD429H5": [],
    "PMU475Y1": [],
    "ENGC26H3": [],
    "ECE355H1": [],
    "RSM404Y1": [],
    "MGAD45H3": [],
    "ECE469H1": [],
    "ECE344H1": [],
    "CSC399Y1": [],
    "COPB11H3": [],
    "NMC378H1": [],
    "ECO101H1": [],
    "HMB306H1": [],
    "JMU305H1": [],
    "PHL244H5": [],
    "FRE283H5": [],
    "CCT481H5": [],
    "SDS458H1": [],
    "ESS324H1": [],
    "BME396H1": [],
    "PSY369H5": [],
    "GGR365H5": [],
    "MAT401H1": [],
    "TMU306H1": [],
    "SOCD21H3": [],
    "MUZA60H3": [],
    "ANTC66H3": [],
    "MGED02H3": [],
    "WSTD16H3": [],
    "PSY290H1": [],
    "CSB397Y0": [],
    "PSCD02H3": [],
    "EAS327H1": [],
    "CTA200H1": [],
    "POLC98H3": [],
    "WRI363H5": [],
    "PHL340H5": [],
    "MSE238H1": [],
    "JOUC31H3": [],
    "CJS498Y1": [],
    "MDSB05H3": [],
    "RLG497Y5": [],
    "GASC20H3": [],
    "ANTC70H3": [],
    "MGEC58H3": [],
    "ANTC24H3": [],
    "MGM466H5": [],
    "PLID07Y3": [],
    "ANTC09H3": [],
    "CIV300H1": [],
    "JMU384Y1": [],
    "CCT355H5": [],
    "LAT211H5": [],
    "TEP447H1": [],
    "SOC492H5": [],
    "MGT323H5": [],
    "DRE122H5": [],
    "ITA219H5": [],
    "ESC471H1": [],
    "ANT343H1": [],
    "PMU387Y1": [],
    "FSC415H5": [],
    "FRED07H3": [],
    "HISC34H3": [],
    "PHL242H5": [],
    "BIO120H1": [],
    "PMU460Y1": [],
    "MSE316H1": [],
    "ERS401H5": [],
    "ESC472H1": [],
    "PHL346H5": [],
    "GGR340H1": [],
    "CLA368H5": [],
    "HLTB30H3": [],
    "ECO381H5": [],
    "EESD31H3": [],
    "SOC302H5": [],
    "CDPD01H3": [],
    "ECE516H1": [],
    "PHL382H1": [],
    "ITA221H5": [],
    "JMU393Y1": [],
    "RLG318H5": [],
    "PHY372H1": [],
    "FAS247H5": [],
    "FSTC02H3": [],
    "PHYB54H3": [],
    "ARC364Y1": [],
    "CHM311H5": [],
    "FOR421H1": [],
    "FRE491H5": [],
    "SMC381Y1": [],
    "ENV492H1": [],
    "ANT207H5": [],
    "CHI203H5": [],
    "PSY392H5": [],
    "POL403H5": [],
    "PHY255H5": [],
    "CIV313H1": [],
    "CSC336H1": [],
    "MSE202H1": [],
    "MGT444H5": [],
    "HISD55H3": [],
    "AER304H1": [],
    "UTM192H5": [],
    "BIO408H5": [],
    "HIS357H5": [],
    "BME346H1": [],
    "LIN251H1": [],
    "SOCB54H3": [],
    "JRE300H1": [],
    "HIS102H5": [],
    "VIS240H1": [],
    "FSC303H5": [],
    "FSC482H5": [],
    "MIE343H1": [],
    "WRI227H5": [],
    "CIV331H1": [],
    "CHI303H5": [],
    "BIOB35H3": [],
    "ARC361Y1": [],
    "MAT224H5": [],
    "WRI292H5": [],
    "MSE492H1": [],
    "ROB311H1": [],
    "EAS296H1": [],
    "PHYC56H3": [],
    "CIV209H1": [],
    "WSTB06H3": [],
    "HLTC48H3": [],
    "PHLB20H3": [],
    "OMU704Y1": [],
    "CHMA11H3": [],
    "AER336H1": [],
    "FAH415H5": [],
    "VIS217H1": [],
    "ESS299Y1": [],
    "LIN208H5": [],
    "MATD46H3": [],
    "LIN241H1": [],
    "PSL300H1": [],
    "PMU135Y1": [],
    "SWK302H1": [],
    "MIE422H1": [],
    "HLTB42H3": [],
    "PSY474H5": [],
    "HLTD22H3": [],
    "FSTD10H3": [],
    "POL214H1": [],
    "POLD95H3": [],
    "VCC390H5": [],
    "MGEB01H3": [],
    "POLD70H3": [],
    "INS302H1": [],
    "LGGA74H3": [],
    "COPA31Y3": [],
    "PHL295H5": [],
    "PSY371H5": [],
    "GGR383H5": [],
    "JOUC63H3": [],
    "STA302H5": [],
    "JHE353H1": [],
    "BIO405H5": [],
    "NMED10Y3": [],
    "HISC73H3": [],
    "WGS373H5": [],
    "MGFD25H3": [],
    "MAT399Y5": [],
    "HLTC55H3": [],
    "BIOD34H3": [],
    "MSE222H1": [],
    "MUZB64H3": [],
    "POL487H1": [],
    "CHM395Y1": [],
    "MIE550H1": [],
    "MGT326H5": [],
    "FREB22H3": [],
    "ANT332H5": [],
    "SOC434H5": [],
    "FREA91Y3": [],
    "CCT335H5": [],
    "CHE412H1": [],
    "PHL432H5": [],
    "HISC58H3": [],
    "RLG346H5": [],
    "POL242Y5": [],
    "BME344H1": [],
    "DRS421H5": [],
    "PSYC31H3": [],
    "MGMD11H3": [],
    "POL340Y5": [],
    "VPSC70H3": [],
    "JQR360H1": [],
    "MDSB15H3": [],
    "FSC314H5": [],
    "MATC15H3": [],
    "LIND09H3": [],
    "APS106H1": [],
    "FAS147H5": [],
    "CCT476H5": [],
    "PSYC27H3": [],
    "OMU706Y1": [],
    "WRI320H5": [],
    "PMU375Y1": [],
    "VPHC49H3": [],
    "PHLB04H3": [],
    "ESC190H1": [],
    "AST110H5": [],
    "ERS404H5": [],
    "SOC465H5": [],
    "SOC334H5": [],
    "ITA231H5": [],
    "GGR353H5": [],
    "PMU426H1": [],
    "PSY290H5": [],
    "ANTB09H3": [],
    "BIOB98H3": [],
    "RLG204H5": [],
    "ANT306H5": [],
    "BIO207H5": [],
    "BIOB33H3": [],
    "CLA303H5": [],
    "SOC306H5": [],
    "CCT365H5": [],
    "IDSB01H3": [],
    "MGEC71H3": [],
    "GGRC10H3": [],
    "POL301Y1": [],
    "CIV191H1": [],
    "ESS410H0": [],
    "HPS371H1": [],
    "PHL100Y1": [],
    "ASTC25H3": [],
    "HIS494H5": [],
    "ENG261H5": [],
    "FAS448Y5": [],
    "LIN366H5": [],
    "POL215H5": [],
    "SOCC34H3": [],
    "WGS366H5": [],
    "CSC358H5": [],
    "CCT470H5": [],
    "VCC306H5": [],
    "URD312Y5": [],
    "PSY328H1": [],
    "MIE354H1": [],
    "EMU231H1": [],
    "SMC433Y1": [],
    "ENG235H1": [],
    "MSE219H1": [],
    "PMU494Y1": [],
    "PSY325H5": [],
    "FAS248H5": [],
    "GER250H5": [],
    "CITD05H3": [],
    "EDS325H5": [],
    "GGR210H5": [],
    "MGMC01H3": [],
    "WSTC28H3": [],
    "WGS410H5": [],
    "CIV185H1": [],
    "RLG306H5": [],
    "PMU487Y1": [],
    "CSB352H1": [],
    "RSM399Y1": [],
    "EESA10H3": [],
    "EUR495H1": [],
    "GGR313H5": [],
    "PSL379H0": [],
    "BIOC15H3": [],
    "WGS415H5": [],
    "STA302H1": [],
    "HMB265H1": [],
    "GGR217H1": [],
    "GGR273H1": [],
    "CIN105Y1": [],
    "SOCC61H3": [],
    "CHE210H1": [],
    "EAS357H1": [],
    "SOC491H1": [],
    "BIOC37H3": [],
    "HISC55H3": [],
    "LAS302H1": [],
    "CCT206H5": [],
    "EESC36H3": [],
    "ACMD92H3": [],
    "NROC93H3": [],
    "POL484Y5": [],
    "APS490Y1": [],
    "SOC230H5": [],
    "HMB434H1": [],
    "RLG203H5": [],
    "WGS345H5": [],
    "ECE552H1": [],
    "MGFD40H3": [],
    "MGEB06H3": [],
    "MGEA01H3": [],
    "SOC491H5": [],
    "WGS340H5": [],
    "CTA299Y1": [],
    "TEP343H1": [],
    "CSCD18H3": [],
    "MATC34H3": [],
    "CHE499Y1": [],
    "PMU384Y1": [],
    "PMU226H1": [],
    "MAT389H1": [],
    "DRS425H5": [],
    "CCT250H5": [],
    "ENGD22H3": [],
    "LTE399Y1": [],
    "TEP432H1": [],
    "PHLC10H3": [],
    "GGR415H5": [],
    "HLTC46H3": [],
    "ANTD22H3": [],
    "NMC260H1": [],
    "PMDC43H3": [],
    "SOC424H5": [],
    "MATA29H3": [],
    "MGT440H5": [],
    "GGRB30H3": [],
    "NEW495Y1": [],
    "AST201H1": [],
    "FAH481Y1": [],
    "AST215H5": [],
    "ARC386H1": [],
    "MSE398Y1": [],
    "VPSB75H3": [],
    "HSC402H5": [],
    "LINC02H3": [],
    "TMU131H1": [],
    "ACMD02H3": [],
    "MAT334H5": [],
    "SMC390Y1": [],
    "SOC325H5": [],
    "VIS204H1": [],
    "CHMD89H3": [],
    "JCP265H5": [],
    "THRB20H3": [],
    "CIV235H1": [],
    "CCT490H5": [],
    "CCT451H5": [],
    "MAT102H5": [],
    "GASC53H3": [],
    "PMU440Y1": [],
    "MATB41H3": [],
    "FREA01H3": [],
    "PHL400H5": [],
    "SOC311H1": [],
    "MGSC35H3": [],
    "PHLD87H3": [],
    "MGID79H3": [],
    "HISB50H3": [],
    "FAS455H5": [],
    "ARC302H1": [],
    "FSC481Y5": [],
    "GGR315H5": [],
    "MATA35H3": [],
    "POL417Y1": [],
    "ANT437H5": [],
    "MGT353H5": [],
    "EESC18H3": [],
    "GGRC09H3": [],
    "BIOC50H3": [],
    "FAS234H5": [],
    "PSY299Y1": [],
    "LIND01H3": [],
    "GGRC34H3": [],
    "MUZB65H3": [],
    "PSYD20H3": [],
    "ECE557H1": [],
    "HLTB50H3": [],
    "FAH327H1": [],
    "ENG203H1": [],
    "ECO365H1": [],
    "HMB499Y1": [],
    "FRE487H5": [],
    "POL336Y5": [],
    "ARC357H1": [],
    "FREC63H3": [],
    "HISC59H3": [],
    "STAC32H3": [],
    "THRC41H3": [],
    "MIE519H1": [],
    "ENGC08H3": [],
    "HPS211H1": [],
    "FSC100H5": [],
    "GGR317H5": [],
    "FSL205Y5": [],
    "OMU510H1": [],
    "SOC331H1": [],
    "PSYD22H3": [],
    "HLTB16H3": [],
    "MDSC01H3": [],
    "WGS375H5": [],
    "ARC281H1": [],
    "ANT314H5": [],
    "CLAA06H3": [],
    "POL305Y5": [],
    "RLG453H5": [],
    "ENGB75H3": [],
    "CHM341H5": [],
    "CIV514H1": [],
    "BIO333H5": [],
    "RLG388H5": [],
    "APS305H1": [],
    "POLD52H3": [],
    "CIV521H1": [],
    "BIOD54H3": [],
    "PSYC08H3": [],
    "SOC494H5": [],
    "PSYB10H3": [],
    "ECTB60H3": [],
    "CLAC22H3": [],
    "CHE475H1": [],
    "TMU133H1": [],
    "MIE504H1": [],
    "DRM387H1": [],
    "PMU183Y1": [],
    "GGRC33H3": [],
    "PHL240H5": [],
    "JOUB05H3": [],
    "TMU311Y1": [],
    "PSY344H5": [],
    "SOC455H5": [],
    "ANTC69H3": [],
    "CSCA20H3": [],
    "PSYC30H3": [],
    "RLG340H5": [],
    "HISB51H3": [],
    "CHE565H1": [],
    "VIS430Y1": [],
    "DRE222H5": [],
    "IDSC18H3": [],
    "LIN495Y5": [],
    "ARA212Y5": [],
    "BIO484H5": [],
    "PMU284Y1": [],
    "JOUC19H3": [],
    "POL346Y5": [],
    "BIO353H5": [],
    "EMU260H1": [],
    "ARC180H1": [],
    "SOC304H5": [],
    "FAH312H1": [],
    "FREA02H3": [],
    "FRE180H5": [],
    "HIS280Y1": [],
    "CSB299Y1": [],
    "RLG206H5": [],
    "DTS200Y1": [],
    "SOC412H1": [],
    "HISB65H3": [],
    "MATC32H3": [],
    "VPSC69H3": [],
    "FSC407H5": [],
    "ENG110H5": [],
    "ENG325H5": [],
    "CSC369H1": [],
    "JMU189Y1": [],
    "ARC451H1": [],
    "SOC499Y5": [],
    "MGSD05H3": [],
    "SOC490Y1": [],
    "MGEC61H3": [],
    "MATC37H3": [],
    "FREB18H3": [],
    "PMU289Y1": [],
    "STAB57H3": [],
    "RLG374H5": [],
    "SOCB22H3": [],
    "CCT386H5": [],
    "BIOC16H3": [],
    "VIS312H1": [],
    "ANTC33H3": [],
    "APS064H1": [],
    "CHE507H1": [],
    "CCT200H5": [],
    "FAS452H5": [],
    "WSTC30H3": [],
    "CITC09H3": [],
    "MIE262H1": [],
    "ANTB20H3": [],
    "CSCC09H3": [],
    "LTL456H5": [],
    "SOCC23H3": [],
    "BME489H1": [],
    "HLTB22H3": [],
    "CCT485H5": [],
    "EEB498Y1": [],
    "POL200Y5": [],
    "IRE430H1": [],
    "CSC375H5": [],
    "ENGB25H3": [],
    "ROB313H1": [],
    "ECE318H1": [],
    "PSL301H1": [],
    "PMU445Y1": [],
    "STA303H1": [],
    "DRE226H5": [],
    "HIS431H5": [],
    "VPHD48H3": [],
    "ENG307H5": [],
    "PMU295Y1": [],
    "GGR265H5": [],
    "STA457H5": [],
    "PMU128H1": [],
    "HMU111H1": [],
    "BIO477H5": [],
    "THRB21H3": [],
    "MIE243H1": [],
    "COPA83Y3": [],
    "PMA490Y1": [],
    "POLB72H3": [],
    "ANT441H1": [],
    "IDSC07H3": [],
    "POL440Y5": [],
    "SOC365H1": [],
    "CCT316H5": [],
    "PHL455H1": [],
    "CHMC31Y3": [],
    "PHLB99H3": [],
    "FSC302H5": [],
    "GGR333H5": [],
    "PHY489Y5": [],
    "EESA11H3": [],
    "CITB04H3": [],
    "VCC101H5": [],
    "CHM436H5": [],
    "CHMC20H3": [],
    "PHL370H5": [],
    "BIO331H5": [],
    "BIO416H5": [],
    "BME445H1": [],
    "FAS245H5": [],
    "CHMB41H3": [],
    "CCT450H5": [],
    "CIV498H1": [],
    "ARC480H1": [],
    "VPHB78H3": [],
    "STAC33H3": [],
    "PSY494H1": [],
    "PSYD30H3": [],
    "PMU336Y1": [],
    "SDS255H1": [],
    "ENG484H1": [],
    "JMU489Y1": [],
    "HIS378H5": [],
    "FREB51H3": [],
    "CCT300H5": [],
    "OMU608H1": [],
    "POL382H1": [],
    "PMA455Y1": [],
    "HIS390H5": [],
    "PSYB20H3": [],
    "JOUB11H3": [],
    "FAH288H5": [],
    "STA257H1": [],
    "BIO310H5": [],
    "CDN355H1": [],
    "ECO370Y5": [],
    "NEW490Y1": [],
    "POLB92H3": [],
    "ARC387H1": [],
    "ENG364Y1": [],
    "MSE191H1": [],
    "FREB44H3": [],
    "HMB200H1": [],
    "FAH382H1": [],
    "MAT322H5": [],
    "HISC94H3": [],
    "JMU192Y1": [],
    "HIS374H5": [],
    "FSC101H5": [],
    "MATD94H3": [],
    "GGRB21H3": [],
    "MGM102H5": [],
    "ENGB22H3": [],
    "SOC378H5": [],
    "CIN260H1": [],
    "IMI302H5": [],
    "ANT370H5": [],
    "ENGC31H3": [],
    "EMU230H1": [],
    "APS440H1": [],
    "PHLD05H3": [],
    "POLD59H3": [],
    "PPGC67H3": [],
    "CJS391H1": [],
    "PMU175Y1": [],
    "CME499Y1": [],
    "MGFC50H3": [],
    "SOC100H5": [],
    "CHE471H1": [],
    "SOC243H1": [],
    "PHYA22H3": [],
    "JEG401Y5": [],
    "POL438H5": [],
    "PMU380Y1": [],
    "CHM416H5": [],
    "ENG357H1": [],
    "RLG211H5": [],
    "CCT418H5": [],
    "DRE362H5": [],
    "PMU361Y1": [],
    "ECE231H1": [],
    "PSY404H5": [],
    "CHM333H5": [],
    "MDSB01H3": [],
    "TMU232H1": [],
    "ANTD15H3": [],
    "BIOD27H3": [],
    "VIS326H1": [],
    "CIN207H5": [],
    "BIOD98Y3": [],
    "PHY327H1": [],
    "PHL258H5": [],
    "WGS470H5": [],
    "HLTD53H3": [],
    "PMA430Y1": [],
    "ESC491H1": [],
    "CHMB42H3": [],
    "FRED90Y3": [],
    "CLA499H5": [],
    "VCC236H5": [],
    "MSE438H1": [],
    "PHY180H1": [],
    "BIO380H5": [],
    "ENGB06H3": [],
    "LTL380H5": [],
    "ROB521H1": [],
    "TMU317H1": [],
    "WRI390H5": [],
    "ECO345H5": [],
    "CJS396H1": [],
    "ANTC03H3": [],
    "PSYC22H3": [],
    "WGS250H5": [],
    "JCB487Y5": [],
    "GGR305H5": [],
    "MIN191H1": [],
    "CCT312H5": [],
    "ECO326H5": [],
    "IMI203H5": [],
    "FAH465H5": [],
    "SOCD13H3": [],
    "ANT317H5": [],
    "LINC11H3": [],
    "STA256H5": [],
    "MAT392H5": [],
    "FSL305Y5": [],
    "HIS497Y5": [],
    "GGR463H5": [],
    "CIN102H5": [],
    "ANT432H5": [],
    "RLG470H5": [],
    "AST221H5": [],
    "CIV250H1": [],
    "MATC01H3": [],
    "AST201H5": [],
    "PSCB90H3": [],
    "ERS499Y5": [],
    "BIO347H5": [],
    "SOC227H5": [],
    "MGT374H5": [],
    "MAT478H5": [],
    "FSL421Y1": [],
    "PHL355H5": [],
    "FREB36H3": [],
    "HISC26H3": [],
    "PSYD54H3": [],
    "RLG307H5": [],
    "COPA86Y3": [],
    "MAT311H5": [],
    "THRB56H3": [],
    "CCT435H5": [],
    "SOC231H5": [],
    "HSC404H5": [],
    "IDSD14H3": [],
    "FAS348Y5": [],
    "AER507H1": [],
    "PHL440H5": [],
    "CHE566H1": [],
    "RLG337H5": [],
    "CSC376H5": [],
    "CHE305H1": [],
    "MSE443H1": [],
    "RLG370H5": [],
    "PHLB58H3": [],
    "GASB77H3": [],
    "WSTD09H3": [],
    "PSYD32H3": [],
    "AER310H1": [],
    "MIE540H1": [],
    "MIE498H1": [],
    "ENV311H5": [],
    "FAH392H5": [],
    "WRI420H5": [],
    "CLAC67H3": [],
    "HIS490H5": [],
    "SOC299Y5": [],
    "POLC36H3": [],
    "ANT441H5": [],
    "HLTC29H3": [],
    "MGEC41H3": [],
    "ENG206H5": [],
    "PMU452Y1": [],
    "VPAA12H3": [],
    "DTS390Y1": [],
    "MSE217H1": [],
    "HIS291H1": [],
    "FAH451H5": [],
    "POL304Y5": [],
    "EESC20H3": [],
    "HMU435H1": [],
    "HIN311H5": [],
    "FRED05H3": [],
    "CHE488H1": [],
    "ANT380H5": [],
    "CCT420H5": [],
    "COG402H1": [],
    "PMU252Y1": [],
    "ANTA01H3": [],
    "HIS338H5": [],
    "HIN211H5": [],
    "SOC317H5": [],
    "POL114H5": [],
    "ACT348H1": [],
    "MGTA02H3": [],
    "BIO152H5": [],
    "ESTD17Y3": [],
    "HIS242H5": [],
    "FSC340H5": [],
    "CHE208H1": [],
    "CITC07H3": [],
    "DRE463H5": [],
    "BIO320H5": [],
    "STA260H5": [],
    "STAD80H3": [],
    "CHM395H5": [],
    "FAH395H5": [],
    "HMU126H1": [],
    "ITA232H5": [],
    "LIN332H5": [],
    "ECE311H1": [],
    "BIO311H5": [],
    "ITA238H5": [],
    "GER490H1": [],
    "CHM231H5": [],
    "EEB398H0": [],
    "CCT218H5": [],
    "MGT300H5": [],
    "ECO375H5": [],
    "CCT308H5": [],
    "CRI225H1": [],
    "GGR335H5": [],
    "CIV515H1": [],
    "GGR276H5": [],
    "PHY299Y1": [],
    "NROB60H3": [],
    "MIE516H1": [],
    "MATC63H3": [],
    "HMU385H1": [],
    "EMU264H1": [],
    "ITA351H5": [],
    "CITC03H3": [],
    "WSTD30H3": [],
    "IDSD19H3": [],
    "PMU305Y1": [],
    "MIE364H1": [],
    "THRA10H3": [],
    "CTLA01H3": [],
    "CHM345H5": [],
    "LIN102H5": [],
    "POLD55H3": [],
    "APS191H1": [],
    "ENV100H1": [],
    "PHLB60H3": [],
    "MIE451H1": [],
    "HIS105H5": [],
    "HISD02H3": [],
    "RLG393H1": [],
    "PHL496H5": [],
    "PMU495Y1": [],
    "FLDA01Y3": [],
    "EDS220H5": [],
    "PHL245H5": [],
    "ENG251H5": [],
    "PHL281H1": [],
    "CSC492H5": [],
    "ESC470H1": [],
    "HLTD80H3": [],
    "MIE441H1": [],
    "MIE505H1": [],
    "MIE498Y1": [],
    "WGS355H5": [],
    "PSYD37H3": [],
    "MSE498Y1": [],
    "ANT318H5": [],
    "ECO359H5": [],
    "WRI307H5": [],
    "FRE225Y5": [],
    "FSC300H5": [],
    "MGHC53H3": [],
    "CLA236H1": [],
    "ERS315H5": [],
    "PHL300H5": [],
    "ECE437H1": [],
    "CIV460H1": [],
    "HIS241H5": [],
    "CCT432H5": [],
    "FAS369Y5": [],
    "MIE458H1": [],
    "ENV221H1": [],
    "ANT354H5": [],
    "ARC381Y1": [],
    "STA399Y1": [],
    "ENGB19H3": [],
    "MAT344H5": [],
    "PSY331H1": [],
    "HIN313H5": [],
    "LIN256H5": [],
    "SOC202H5": [],
    "CIN302H5": [],
    "MGT301H5": [],
    "MGOC10H3": [],
    "PHL358H5": [],
    "CHI310H5": [],
    "NEW491H1": [],
    "ANTC14H3": [],
    "PHY433H5": [],
    "ENV310H5": [],
    "PMU210Y1": [],
    "CCT452H5": [],
    "ANTC16H3": [],
    "GRK428H1": [],
    "WSTC26H3": [],
    "PSY379H5": [],
    "NROC90H3": [],
    "HISD65H3": [],
    "ANTD06H3": [],
    "CSC299Y5": [],
    "WGS200Y5": [],
    "ECO206Y5": [],
    "RLG378H5": [],
    "CHI212H5": [],
    "MSE120H1": [],
    "ANTD20H3": [],
    "NMEB06H3": [],
    "LIN228H1": [],
    "FAH292H5": [],
    "PMDC54Y3": [],
    "SOC446H5": [],
    "AER506H1": [],
    "VIS330H1": [],
    "HMU324H1": [],
    "MDSC65H3": [],
    "JMU284Y1": [],
    "FAS454H5": [],
    "PCL474Y1": [],
    "PSY328H5": [],
    "CSCB58H3": [],
    "ENV330H5": [],
    "PMA475Y1": [],
    "CCT314H5": [],
    "DRE305H5": [],
    "VPSB61H3": [],
    "PSY333H5": [],
    "EESC24H3": [],
    "CCT204H5": [],
    "WGS335H5": [],
    "COPA79Y3": [],
    "CSCC01H3": [],
    "CCT434H5": [],
    "MATA02H3": [],
    "ENG372H5": [],
    "PMU407H1": [],
    "BIOC31H3": [],
    "ENGB76H3": [],
    "CHE211H1": [],
    "NMC275H1": [],
    "CITB01H3": [],
    "MAT235Y1": [],
    "SOC202H1": [],
    "GASB05H3": [],
    "PSYB64H3": [],
    "PMU310Y1": [],
    "MGTA05H3": [],
    "MGM390H5": [],
    "HMU499H1": [],
    "PMU129H1": [],
    "PHY241H5": [],
    "FAS359Y5": [],
    "BIO318Y5": [],
    "ERS202H5": [],
    "VPHC72H3": [],
    "GGRC42H3": [],
    "CHM414H5": [],
    "ENGC38H3": [],
    "CSC494H1": [],
    "SOC405H5": [],
    "CJS499H1": [],
    "CSCD94H3": [],
    "EESC03H3": [],
    "EDS210H5": [],
    "POL209H5": [],
    "LGGC65H3": [],
    "SOC422H1": [],
    "PMU394Y1": [],
    "ECO102H5": [],
    "JOUB24H3": [],
    "PMU275Y1": [],
    "STA107H5": [],
    "GER260Y1": [],
    "FRE363H5": [],
    "ITA496Y5": [],
    "HIS212H5": [],
    "ECE358H1": [],
    "SOC379H5": [],
    "TRN305Y1": [],
    "HMB433H1": [],
    "BIOD63H3": [],
    "CCT473H5": [],
    "PHY132H1": [],
    "POLC53H3": [],
    "ENGD27Y3": [],
    "PMU455Y1": [],
    "TMU499Y1": [],
    "STA312H5": [],
    "PSY202H5": [],
    "GGRD10H3": [],
    "PHL255H5": [],
    "GGR208H5": [],
    "ECE334H1": [],
    "ANT204H1": [],
    "MSE351H1": [],
    "POL368H5": [],
    "TMU113H1": [],
    "HISB11H3": [],
    "MSE430H1": [],
    "CSCD95H3": [],
    "RSM392H1": [],
    "COPB30H3": [],
    "NEW390Y1": [],
    "PSY313H1": [],
    "CIN309H5": [],
    "EMU415H1": [],
    "FRE490Y5": [],
    "RLG420H5": [],
    "EESA09H3": [],
    "CRI350H1": [],
    "POL340Y1": [],
    "ENGD18H3": [],
    "ECE324H1": [],
    "GGRC43H3": [],
    "HIS499Y5": [],
    "PHL410H5": [],
    "JCP410H5": [],
    "RSM100H1": [],
    "ENGB29H3": [],
    "SOC429H5": [],
    "POL490H5": [],
    "ENG287H1": [],
    "PMU491Y1": [],
    "POLB90H3": [],
    "ANTC88H3": [],
    "FAH424H5": [],
    "DRS422H5": [],
    "ACT247H1": [],
    "ECO311H5": [],
    "ENG259H5": [],
    "COPB10Y3": [],
    "CCT261H5": [],
    "SOCB60H3": [],
    "PSYB03H3": [],
    "EESC04H3": [],
    "FAS443Y5": [],
    "MSE343H1": [],
    "MUZB20H3": [],
    "RLG450H5": [],
    "HISC57H3": [],
    "JOUB20H3": [],
    "ERS311H5": [],
    "BIOA11H3": [],
    "ENGC83H3": [],
    "PSY324H5": [],
    "ITA100Y5": [],
    "PSY397H5": [],
    "MAT332H5": [],
    "SOC420H5": [],
    "WGS482H1": [],
    "FRE482H5": [],
    "ANT358H1": [],
    "HISC06H3": [],
    "PHLC60H3": [],
    "EMU410H1": [],
    "COG498H1": [],
    "ANT465H5": [],
    "BIOB32H3": [],
    "MUZB21H3": [],
    "TMU316H1": [],
    "PHL204H5": [],
    "HLTB44H3": [],
    "POL327Y5": [],
    "SOC483H1": [],
    "ITA218H5": [],
    "ANT101H5": [],
    "VPHB77H3": [],
    "JAV151H1": [],
    "ARC466H1": [],
    "VIS208H1": [],
    "CCT417H5": [],
    "CCT381H5": [],
    "CHMB20H3": [],
    "ECE349H1": [],
    "MGAB01H3": [],
    "FRE352H5": [],
    "BIOC58H3": [],
    "BIO313H5": [],
    "BIO476H5": [],
    "GASB65H3": [],
    "MAT315H5": [],
    "FOR200H1": [],
    "MATB61H3": [],
    "CIN380H1": [],
    "PHLC31H3": [],
    "POLD91H3": [],
    "ESC301H1": [],
    "MAT301H1": [],
    "STAD29H3": [],
    "HIS398H5": [],
    "FRE492H5": [],
    "ENGB07H3": [],
    "PHLC51H3": [],
    "ENG100H5": [],
    "PHY427H1": [],
    "ESS234H1": [],
    "MAT291H1": [],
    "POLC34H3": [],
    "PSYC13H3": [],
    "GGRD01H3": [],
    "EESB18H3": [],
    "ERS304H5": [],
    "PMU215Y1": [],
    "PHL103H5": [],
    "OMU610H1": [],
    "SOC371H5": [],
    "CHM372H5": [],
    "BIOC40H3": [],
    "GGR484H5": [],
    "ENG314H5": [],
    "VPSA63H3": [],
    "CITC01H3": [],
    "LINC10H3": [],
    "VPSD57H3": [],
    "POL299Y1": [],
    "BIOC90H3": [],
    "PSY240H5": [],
    "MGIB02H3": [],
    "ECE259H1": [],
    "FAH205H5": [],
    "PSY410H5": [],
    "NMEC01H3": [],
    "MATD34H3": [],
    "SOCB49H3": [],
    "HIS255H5": [],
    "ENGC88H3": [],
    "FSC483H5": [],
    "TMU307H1": [],
    "ITA388H5": [],
    "AST251H1": [],
    "HISD35H3": [],
    "CHE249H1": [],
    "ENG273H5": [],
    "CCT440H5": [],
    "BCH372Y1": [],
    "EESB02H3": [],
    "MIE533H1": [],
    "EESD19H3": [],
    "GASD02H3": [],
    "PHLD31H3": [],
    "FSC361H5": [],
    "HLTC27H3": [],
    "CSC236H1": [],
    "FAH390H5": [],
    "CLA320H5": [],
    "AER210H1": [],
    "MGHD27H3": [],
    "STA348H5": [],
    "POLC21H3": [],
    "APS162H1": [],
    "ANT214H5": [],
    "MGIC02H3": [],
    "AER501H1": [],
    "MSE355H1": [],
    "MAT299Y5": [],
    "PMU229H1": [],
    "ENG205H5": [],
    "ANTB16H3": [],
    "MGT311H5": [],
    "CHMD47H3": [],
    "POLB81H3": [],
    "ANT368H5": [],
    "PMA485Y1": [],
    "ANT415H5": [],
    "CHE221H1": [],
    "VCC205H5": [],
    "PUN212Y5": [],
    "FSC315H5": [],
    "LIN101H1": [],
    "GASD30H3": [],
    "MATC90H3": [],
    "WGS367H1": [],
    "CHMB21H3": [],
    "MGHD26H3": [],
    "GASD71H3": [],
    "ITA247H5": [],
    "BIO475H5": [],
    "PHYA11H3": [],
    "PHYD37H3": [],
    "STAC50H3": [],
    "CSCA08H3": [],
    "FSL100H1": [],
    "CHI313H5": [],
    "PHL325H5": [],
    "GGR311H5": [],
    "CHMB62H3": [],
    "MSE455H1": [],
    "CHI403H5": [],
    "MGTD82Y3": [],
    "OMU722Y1": [],
    "POLC91H3": [],
    "ANT100Y1": [],
    "CDN335H1": [],
    "HIS395H5": [],
    "SOCC37H3": [],
    "ENG122H5": [],
    "CCT340H5": [],
    "ERS203H5": [],
    "EMU245H1": [],
    "LIND07Y3": [],
    "RLG401H5": [],
    "ENG289H5": [],
    "ACT245H1": [],
    "EAS110Y1": [],
    "FOR425H1": [],
    "DRS426H5": [],
    "SOC454H5": [],
    "MGMC12H3": [],
    "PSY372H5": [],
    "EESC16H3": [],
    "LAT101H1": [],
    "MSE459H1": [],
    "PHL293H5": [],
    "COPA90Y3": [],
    "LAT102H1": [],
    "ENGA11H3": [],
    "BIO419H5": [],
    "CCT495H5": [],
    "EEB399Y1": [],
    "CHE213H1": [],
    "MGM465H5": [],
    "PSY424H1": [],
    "CHM211H5": [],
    "HLTD11H3": [],
    "ESS324H0": [],
    "COG499H1": [],
    "DRE360H5": [],
    "BIOD20H3": [],
    "PHLB50H3": [],
    "ECE446H1": [],
    "FREB55H3": [],
    "LMP299Y1": [],
    "VCC400H5": [],
    "MGEC54H3": [],
    "FREB84H3": [],
    "PSY220H5": [],
    "RLG201H5": [],
    "MATD02H3": [],
    "EAS273H1": [],
    "ENG239H5": [],
    "ECE241H1": [],
    "SOC253H5": [],
    "NFS284H1": [],
    "COPB33H3": [],
    "LIN279Y5": [],
    "CSC165H1": [],
    "MAT234H1": [],
    "PHLD85H3": [],
    "ANT499H1": [],
    "MAT133Y1": [],
    "EDS300H5": [],
    "HMB437H1": [],
    "CITC14H3": [],
    "PHL301H5": [],
    "CSCD01H3": [],
    "HMB360H1": [],
    "FSTC43H3": [],
    "JMU392Y1": [],
    "MGIA01H3": [],
    "WRI378H5": [],
    "FSC416H5": [],
    "EESD20H3": [],
    "OMU641Y1": [],
    "NEW280Y1": [],
    "HISC39H3": [],
    "WRI360H5": [],
    "MGAC10H3": [],
    "ENGC87H3": [],
    "ARC181H1": [],
    "MIE368H1": [],
    "PCJ499H1": [],
    "POLD58H3": [],
    "JMU292Y1": [],
    "CSCC11H3": [],
    "HLTD44H3": [],
    "LIN380H5": [],
    "VPSB56H3": [],
    "CSCC69H3": [],
    "MIE237H1": [],
    "CSC369H5": [],
    "CPS401Y5": [],
    "STA437H5": [],
    "VPSB89H3": [],
    "MIE463H1": [],
    "POL355Y5": [],
    "POL201H1": [],
    "PHLB91H3": [],
    "LIN357H5": [],
    "ANTD32H3": [],
    "MUZB02H3": [],
    "PHL271H1": [],
    "PSYD33H3": [],
    "CCT202H5": [],
    "CSB499Y1": [],
    "MGT455H5": [],
    "CSB346H1": [],
    "OMU604Y1": [],
    "WRI488H5": [],
    "MGSC30H3": [],
    "PMU350Y1": [],
    "MUZC21H3": [],
    "CME259H1": [],
    "VPHC75H3": [],
    "RSM222H1": [],
    "PSY402H1": [],
    "ARC201H1": [],
    "FAH455H5": [],
    "POL476H5": [],
    "MGIB01H3": [],
    "MAT186H1": [],
    "MIN467H1": [],
    "IDSB02H3": [],
    "ENG350H5": [],
    "MGM221H5": [],
    "ENGC79H3": [],
    "VPAC18H3": [],
    "HIS410H5": [],
    "POLC59H3": [],
    "FAH495H5": [],
    "ANTC68H3": [],
    "PMU376Y1": [],
    "FREC10H3": [],
    "JOUA06H3": [],
    "STAC63H3": [],
    "HIS406H1": [],
    "ENV320H5": [],
    "FAS347Y5": [],
    "HIS264H1": [],
    "CCT448H5": [],
    "ANT208H1": [],
    "PMU379Y1": [],
    "EAS496H1": [],
    "PHL354H5": [],
    "ECE331H1": [],
    "MGT224H5": [],
    "RLG461H5": [],
    "NROC69H3": [],
    "JMU200Y1": [],
    "WGS334H1": [],
    "ECO343H5": [],
    "HIS372H5": [],
    "COPA87Y3": [],
    "HISD01H3": [],
    "STAC58H3": [],
    "NROC36H3": [],
    "CIV531H1": [],
    "FAH394H5": [],
    "DRE392H5": [],
    "CHM444H5": [],
    "ECO364H1": [],
    "RLG360H5": [],
    "PMU395Y1": [],
    "PSYD18H3": [],
    "CCT203H5": [],
    "ANT462H5": [],
    "CHI404H5": [],
    "ECO352H5": [],
    "MAT135H5": [],
    "HLTD56H3": [],
    "ECE314H1": [],
    "CITC16H3": [],
    "WSTB05H3": [],
    "CTLB03H3": [],
    "STA238H1": [],
    "FSC320H5": [],
    "LINA02H3": [],
    "MGT435H5": [],
    "PES100H1": [],
    "PSY321H1": [],
    "VPAD12H3": [],
    "BIO370Y5": [],
    "TMU110H1": [],
    "ENG250H1": [],
    "VIS406H1": [],
    "RLG348H5": [],
    "THRD56H3": [],
    "GASC59H3": [],
    "ACMD91H3": [],
    "HIS438H5": [],
    "ANTC48H3": [],
    "PHY472H1": [],
    "CIV577H1": [],
    "PSYC62H3": [],
    "POLB80H3": [],
    "MIE377H1": [],
    "GRK102H1": [],
    "SOC150H1": [],
    "PSYC33H3": [],
    "MDSB03H3": [],
    "PMU479Y1": [],
    "MDSB61H3": [],
    "BME498Y1": [],
    "CIV401H1": [],
    "APS111H1": [],
    "BME428H1": [],
    "ECE320H1": [],
    "ENG373H5": [],
    "RLG492H1": [],
    "PSY499H5": [],
    "RLG202H5": [],
    "LIN228H5": [],
    "LIN454H5": [],
    "ENGB60H3": [],
    "ENG337H5": [],
    "APM462H1": [],
    "LMP399Y1": [],
    "BIO328H5": [],
    "PMU354Y1": [],
    "ECE412H1": [],
    "ECE330H1": [],
    "HISD51H3": [],
    "ITA499H5": [],
    "SOC463H5": [],
    "HISD25H3": [],
    "ECE431H1": [],
    "CHE333H1": [],
    "MGD428H5": [],
    "ENG357H5": [],
    "STA488H5": [],
    "ECO422H1": [],
    "MGT371H5": [],
    "GASC40H3": [],
    "JLP374H1": [],
    "DRM286H1": [],
    "GGR461H5": [],
    "FREB70H3": [],
    "NROC61H3": [],
    "MAT301H5": [],
    "BIOB34H3": [],
    "BIO315H5": [],
    "TESTCOURSE": [
        {
            "name": "Jimmy",
            "review": "I like this course"
        },
        {
            "name": "James",
            "review": "I didn't really like this course"
        },
        {
            "name": "BOT",
            "review": "I Love this course"
        },
        {
            "name": "BOT",
            "review": "I Love this course"
        }
    ]
}